{"nodes": [{"id": "c_users_akrap_weather_station_lib_tinyusb_lib_freertos_kernel_stream_buffer_c", "label": "stream_buffer.c", "file_type": "code", "source_file": "C:\\Users\\akrap\\weather-station\\lib\\tinyusb\\lib\\FreeRTOS-Kernel\\stream_buffer.c", "source_location": "L1"}, {"id": "freertos_kernel_stream_buffer_prvinitialisenewstreambuffer", "label": "prvInitialiseNewStreamBuffer()", "file_type": "code", "source_file": "C:\\Users\\akrap\\weather-station\\lib\\tinyusb\\lib\\FreeRTOS-Kernel\\stream_buffer.c", "source_location": "L309"}, {"id": "freertos_kernel_stream_buffer_xstreambuffergenericcreatestatic", "label": "xStreamBufferGenericCreateStatic()", "file_type": "code", "source_file": "C:\\Users\\akrap\\weather-station\\lib\\tinyusb\\lib\\FreeRTOS-Kernel\\stream_buffer.c", "source_location": "L409"}, {"id": "freertos_kernel_stream_buffer_xstreambuffergetstaticbuffers", "label": "xStreamBufferGetStaticBuffers()", "file_type": "code", "source_file": "C:\\Users\\akrap\\weather-station\\lib\\tinyusb\\lib\\FreeRTOS-Kernel\\stream_buffer.c", "source_location": "L499"}, {"id": "freertos_kernel_stream_buffer_vstreambufferdelete", "label": "vStreamBufferDelete()", "file_type": "code", "source_file": "C:\\Users\\akrap\\weather-station\\lib\\tinyusb\\lib\\FreeRTOS-Kernel\\stream_buffer.c", "source_location": "L533"}, {"id": "freertos_kernel_stream_buffer_xstreambufferreset", "label": "xStreamBufferReset()", "file_type": "code", "source_file": "C:\\Users\\akrap\\weather-station\\lib\\tinyusb\\lib\\FreeRTOS-Kernel\\stream_buffer.c", "source_location": "L570"}, {"id": "freertos_kernel_stream_buffer_xstreambuffersettriggerlevel", "label": "xStreamBufferSetTriggerLevel()", "file_type": "code", "source_file": "C:\\Users\\akrap\\weather-station\\lib\\tinyusb\\lib\\FreeRTOS-Kernel\\stream_buffer.c", "source_location": "L631"}, {"id": "freertos_kernel_stream_buffer_xstreambufferspacesavailable", "label": "xStreamBufferSpacesAvailable()", "file_type": "code", "source_file": "C:\\Users\\akrap\\weather-station\\lib\\tinyusb\\lib\\FreeRTOS-Kernel\\stream_buffer.c", "source_location": "L665"}, {"id": "freertos_kernel_stream_buffer_xstreambufferbytesavailable", "label": "xStreamBufferBytesAvailable()", "file_type": "code", "source_file": "C:\\Users\\akrap\\weather-station\\lib\\tinyusb\\lib\\FreeRTOS-Kernel\\stream_buffer.c", "source_location": "L702"}, {"id": "freertos_kernel_stream_buffer_xstreambuffersend", "label": "xStreamBufferSend()", "file_type": "code", "source_file": "C:\\Users\\akrap\\weather-station\\lib\\tinyusb\\lib\\FreeRTOS-Kernel\\stream_buffer.c", "source_location": "L719"}, {"id": "freertos_kernel_stream_buffer_xstreambuffersendfromisr", "label": "xStreamBufferSendFromISR()", "file_type": "code", "source_file": "C:\\Users\\akrap\\weather-station\\lib\\tinyusb\\lib\\FreeRTOS-Kernel\\stream_buffer.c", "source_location": "L854"}, {"id": "freertos_kernel_stream_buffer_prvwritemessagetobuffer", "label": "prvWriteMessageToBuffer()", "file_type": "code", "source_file": "C:\\Users\\akrap\\weather-station\\lib\\tinyusb\\lib\\FreeRTOS-Kernel\\stream_buffer.c", "source_location": "L908"}, {"id": "freertos_kernel_stream_buffer_xstreambufferreceive", "label": "xStreamBufferReceive()", "file_type": "code", "source_file": "C:\\Users\\akrap\\weather-station\\lib\\tinyusb\\lib\\FreeRTOS-Kernel\\stream_buffer.c", "source_location": "L961"}, {"id": "freertos_kernel_stream_buffer_xstreambuffernextmessagelengthbytes", "label": "xStreamBufferNextMessageLengthBytes()", "file_type": "code", "source_file": "C:\\Users\\akrap\\weather-station\\lib\\tinyusb\\lib\\FreeRTOS-Kernel\\stream_buffer.c", "source_location": "L1069"}, {"id": "freertos_kernel_stream_buffer_xstreambufferreceivefromisr", "label": "xStreamBufferReceiveFromISR()", "file_type": "code", "source_file": "C:\\Users\\akrap\\weather-station\\lib\\tinyusb\\lib\\FreeRTOS-Kernel\\stream_buffer.c", "source_location": "L1113"}, {"id": "freertos_kernel_stream_buffer_prvreadmessagefrombuffer", "label": "prvReadMessageFromBuffer()", "file_type": "code", "source_file": "C:\\Users\\akrap\\weather-station\\lib\\tinyusb\\lib\\FreeRTOS-Kernel\\stream_buffer.c", "source_location": "L1173"}, {"id": "freertos_kernel_stream_buffer_xstreambufferisempty", "label": "xStreamBufferIsEmpty()", "file_type": "code", "source_file": "C:\\Users\\akrap\\weather-station\\lib\\tinyusb\\lib\\FreeRTOS-Kernel\\stream_buffer.c", "source_location": "L1228"}, {"id": "freertos_kernel_stream_buffer_xstreambufferisfull", "label": "xStreamBufferIsFull()", "file_type": "code", "source_file": "C:\\Users\\akrap\\weather-station\\lib\\tinyusb\\lib\\FreeRTOS-Kernel\\stream_buffer.c", "source_location": "L1256"}, {"id": "freertos_kernel_stream_buffer_xstreambuffersendcompletedfromisr", "label": "xStreamBufferSendCompletedFromISR()", "file_type": "code", "source_file": "C:\\Users\\akrap\\weather-station\\lib\\tinyusb\\lib\\FreeRTOS-Kernel\\stream_buffer.c", "source_location": "L1295"}, {"id": "freertos_kernel_stream_buffer_xstreambufferreceivecompletedfromisr", "label": "xStreamBufferReceiveCompletedFromISR()", "file_type": "code", "source_file": "C:\\Users\\akrap\\weather-station\\lib\\tinyusb\\lib\\FreeRTOS-Kernel\\stream_buffer.c", "source_location": "L1330"}, {"id": "freertos_kernel_stream_buffer_prvwritebytestobuffer", "label": "prvWriteBytesToBuffer()", "file_type": "code", "source_file": "C:\\Users\\akrap\\weather-station\\lib\\tinyusb\\lib\\FreeRTOS-Kernel\\stream_buffer.c", "source_location": "L1365"}, {"id": "freertos_kernel_stream_buffer_prvreadbytesfrombuffer", "label": "prvReadBytesFromBuffer()", "file_type": "code", "source_file": "C:\\Users\\akrap\\weather-station\\lib\\tinyusb\\lib\\FreeRTOS-Kernel\\stream_buffer.c", "source_location": "L1411"}, {"id": "freertos_kernel_stream_buffer_prvbytesinbuffer", "label": "prvBytesInBuffer()", "file_type": "code", "source_file": "C:\\Users\\akrap\\weather-station\\lib\\tinyusb\\lib\\FreeRTOS-Kernel\\stream_buffer.c", "source_location": "L1455"}, {"id": "freertos_kernel_stream_buffer_uxstreambuffergetstreambuffernumber", "label": "uxStreamBufferGetStreamBufferNumber()", "file_type": "code", "source_file": "C:\\Users\\akrap\\weather-station\\lib\\tinyusb\\lib\\FreeRTOS-Kernel\\stream_buffer.c", "source_location": "L1524"}, {"id": "freertos_kernel_stream_buffer_vstreambuffersetstreambuffernumber", "label": "vStreamBufferSetStreamBufferNumber()", "file_type": "code", "source_file": "C:\\Users\\akrap\\weather-station\\lib\\tinyusb\\lib\\FreeRTOS-Kernel\\stream_buffer.c", "source_location": "L1538"}, {"id": "freertos_kernel_stream_buffer_ucstreambuffergetstreambuffertype", "label": "ucStreamBufferGetStreamBufferType()", "file_type": "code", "source_file": "C:\\Users\\akrap\\weather-station\\lib\\tinyusb\\lib\\FreeRTOS-Kernel\\stream_buffer.c", "source_location": "L1553"}], "edges": [{"source": "c_users_akrap_weather_station_lib_tinyusb_lib_freertos_kernel_stream_buffer_c", "target": "string", "relation": "imports", "context": "import", "confidence": "EXTRACTED", "source_file": "C:\\Users\\akrap\\weather-station\\lib\\tinyusb\\lib\\FreeRTOS-Kernel\\stream_buffer.c", "source_location": "L30", "weight": 1.0}, {"source": "c_users_akrap_weather_station_lib_tinyusb_lib_freertos_kernel_stream_buffer_c", "target": "freertos", "relation": "imports", "context": "import", "confidence": "EXTRACTED", "source_file": "C:\\Users\\akrap\\weather-station\\lib\\tinyusb\\lib\\FreeRTOS-Kernel\\stream_buffer.c", "source_location": "L38", "weight": 1.0}, {"source": "c_users_akrap_weather_station_lib_tinyusb_lib_freertos_kernel_stream_buffer_c", "target": "task", "relation": "imports", "context": "import", "confidence": "EXTRACTED", "source_file": "C:\\Users\\akrap\\weather-station\\lib\\tinyusb\\lib\\FreeRTOS-Kernel\\stream_buffer.c", "source_location": "L39", "weight": 1.0}, {"source": "c_users_akrap_weather_station_lib_tinyusb_lib_freertos_kernel_stream_buffer_c", "target": "stream_buffer", "relation": "imports", "context": "import", "confidence": "EXTRACTED", "source_file": "C:\\Users\\akrap\\weather-station\\lib\\tinyusb\\lib\\FreeRTOS-Kernel\\stream_buffer.c", "source_location": "L40", "weight": 1.0}, {"source": "c_users_akrap_weather_station_lib_tinyusb_lib_freertos_kernel_stream_buffer_c", "target": "freertos_kernel_stream_buffer_prvinitialisenewstreambuffer", "relation": "contains", "confidence": "EXTRACTED", "source_file": "C:\\Users\\akrap\\weather-station\\lib\\tinyusb\\lib\\FreeRTOS-Kernel\\stream_buffer.c", "source_location": "L309", "weight": 1.0}, {"source": "c_users_akrap_weather_station_lib_tinyusb_lib_freertos_kernel_stream_buffer_c", "target": "freertos_kernel_stream_buffer_xstreambuffergenericcreatestatic", "relation": "contains", "confidence": "EXTRACTED", "source_file": "C:\\Users\\akrap\\weather-station\\lib\\tinyusb\\lib\\FreeRTOS-Kernel\\stream_buffer.c", "source_location": "L409", "weight": 1.0}, {"source": "c_users_akrap_weather_station_lib_tinyusb_lib_freertos_kernel_stream_buffer_c", "target": "freertos_kernel_stream_buffer_xstreambuffergetstaticbuffers", "relation": "contains", "confidence": "EXTRACTED", "source_file": "C:\\Users\\akrap\\weather-station\\lib\\tinyusb\\lib\\FreeRTOS-Kernel\\stream_buffer.c", "source_location": "L499", "weight": 1.0}, {"source": "c_users_akrap_weather_station_lib_tinyusb_lib_freertos_kernel_stream_buffer_c", "target": "freertos_kernel_stream_buffer_vstreambufferdelete", "relation": "contains", "confidence": "EXTRACTED", "source_file": "C:\\Users\\akrap\\weather-station\\lib\\tinyusb\\lib\\FreeRTOS-Kernel\\stream_buffer.c", "source_location": "L533", "weight": 1.0}, {"source": "c_users_akrap_weather_station_lib_tinyusb_lib_freertos_kernel_stream_buffer_c", "target": "freertos_kernel_stream_buffer_xstreambufferreset", "relation": "contains", "confidence": "EXTRACTED", "source_file": "C:\\Users\\akrap\\weather-station\\lib\\tinyusb\\lib\\FreeRTOS-Kernel\\stream_buffer.c", "source_location": "L570", "weight": 1.0}, {"source": "c_users_akrap_weather_station_lib_tinyusb_lib_freertos_kernel_stream_buffer_c", "target": "freertos_kernel_stream_buffer_xstreambuffersettriggerlevel", "relation": "contains", "confidence": "EXTRACTED", "source_file": "C:\\Users\\akrap\\weather-station\\lib\\tinyusb\\lib\\FreeRTOS-Kernel\\stream_buffer.c", "source_location": "L631", "weight": 1.0}, {"source": "c_users_akrap_weather_station_lib_tinyusb_lib_freertos_kernel_stream_buffer_c", "target": "freertos_kernel_stream_buffer_xstreambufferspacesavailable", "relation": "contains", "confidence": "EXTRACTED", "source_file": "C:\\Users\\akrap\\weather-station\\lib\\tinyusb\\lib\\FreeRTOS-Kernel\\stream_buffer.c", "source_location": "L665", "weight": 1.0}, {"source": "c_users_akrap_weather_station_lib_tinyusb_lib_freertos_kernel_stream_buffer_c", "target": "freertos_kernel_stream_buffer_xstreambufferbytesavailable", "relation": "contains", "confidence": "EXTRACTED", "source_file": "C:\\Users\\akrap\\weather-station\\lib\\tinyusb\\lib\\FreeRTOS-Kernel\\stream_buffer.c", "source_location": "L702", "weight": 1.0}, {"source": "c_users_akrap_weather_station_lib_tinyusb_lib_freertos_kernel_stream_buffer_c", "target": "freertos_kernel_stream_buffer_xstreambuffersend", "relation": "contains", "confidence": "EXTRACTED", "source_file": "C:\\Users\\akrap\\weather-station\\lib\\tinyusb\\lib\\FreeRTOS-Kernel\\stream_buffer.c", "source_location": "L719", "weight": 1.0}, {"source": "c_users_akrap_weather_station_lib_tinyusb_lib_freertos_kernel_stream_buffer_c", "target": "freertos_kernel_stream_buffer_xstreambuffersendfromisr", "relation": "contains", "confidence": "EXTRACTED", "source_file": "C:\\Users\\akrap\\weather-station\\lib\\tinyusb\\lib\\FreeRTOS-Kernel\\stream_buffer.c", "source_location": "L854", "weight": 1.0}, {"source": "c_users_akrap_weather_station_lib_tinyusb_lib_freertos_kernel_stream_buffer_c", "target": "freertos_kernel_stream_buffer_prvwritemessagetobuffer", "relation": "contains", "confidence": "EXTRACTED", "source_file": "C:\\Users\\akrap\\weather-station\\lib\\tinyusb\\lib\\FreeRTOS-Kernel\\stream_buffer.c", "source_location": "L908", "weight": 1.0}, {"source": "c_users_akrap_weather_station_lib_tinyusb_lib_freertos_kernel_stream_buffer_c", "target": "freertos_kernel_stream_buffer_xstreambufferreceive", "relation": "contains", "confidence": "EXTRACTED", "source_file": "C:\\Users\\akrap\\weather-station\\lib\\tinyusb\\lib\\FreeRTOS-Kernel\\stream_buffer.c", "source_location": "L961", "weight": 1.0}, {"source": "c_users_akrap_weather_station_lib_tinyusb_lib_freertos_kernel_stream_buffer_c", "target": "freertos_kernel_stream_buffer_xstreambuffernextmessagelengthbytes", "relation": "contains", "confidence": "EXTRACTED", "source_file": "C:\\Users\\akrap\\weather-station\\lib\\tinyusb\\lib\\FreeRTOS-Kernel\\stream_buffer.c", "source_location": "L1069", "weight": 1.0}, {"source": "c_users_akrap_weather_station_lib_tinyusb_lib_freertos_kernel_stream_buffer_c", "target": "freertos_kernel_stream_buffer_xstreambufferreceivefromisr", "relation": "contains", "confidence": "EXTRACTED", "source_file": "C:\\Users\\akrap\\weather-station\\lib\\tinyusb\\lib\\FreeRTOS-Kernel\\stream_buffer.c", "source_location": "L1113", "weight": 1.0}, {"source": "c_users_akrap_weather_station_lib_tinyusb_lib_freertos_kernel_stream_buffer_c", "target": "freertos_kernel_stream_buffer_prvreadmessagefrombuffer", "relation": "contains", "confidence": "EXTRACTED", "source_file": "C:\\Users\\akrap\\weather-station\\lib\\tinyusb\\lib\\FreeRTOS-Kernel\\stream_buffer.c", "source_location": "L1173", "weight": 1.0}, {"source": "c_users_akrap_weather_station_lib_tinyusb_lib_freertos_kernel_stream_buffer_c", "target": "freertos_kernel_stream_buffer_xstreambufferisempty", "relation": "contains", "confidence": "EXTRACTED", "source_file": "C:\\Users\\akrap\\weather-station\\lib\\tinyusb\\lib\\FreeRTOS-Kernel\\stream_buffer.c", "source_location": "L1228", "weight": 1.0}, {"source": "c_users_akrap_weather_station_lib_tinyusb_lib_freertos_kernel_stream_buffer_c", "target": "freertos_kernel_stream_buffer_xstreambufferisfull", "relation": "contains", "confidence": "EXTRACTED", "source_file": "C:\\Users\\akrap\\weather-station\\lib\\tinyusb\\lib\\FreeRTOS-Kernel\\stream_buffer.c", "source_location": "L1256", "weight": 1.0}, {"source": "c_users_akrap_weather_station_lib_tinyusb_lib_freertos_kernel_stream_buffer_c", "target": "freertos_kernel_stream_buffer_xstreambuffersendcompletedfromisr", "relation": "contains", "confidence": "EXTRACTED", "source_file": "C:\\Users\\akrap\\weather-station\\lib\\tinyusb\\lib\\FreeRTOS-Kernel\\stream_buffer.c", "source_location": "L1295", "weight": 1.0}, {"source": "c_users_akrap_weather_station_lib_tinyusb_lib_freertos_kernel_stream_buffer_c", "target": "freertos_kernel_stream_buffer_xstreambufferreceivecompletedfromisr", "relation": "contains", "confidence": "EXTRACTED", "source_file": "C:\\Users\\akrap\\weather-station\\lib\\tinyusb\\lib\\FreeRTOS-Kernel\\stream_buffer.c", "source_location": "L1330", "weight": 1.0}, {"source": "c_users_akrap_weather_station_lib_tinyusb_lib_freertos_kernel_stream_buffer_c", "target": "freertos_kernel_stream_buffer_prvwritebytestobuffer", "relation": "contains", "confidence": "EXTRACTED", "source_file": "C:\\Users\\akrap\\weather-station\\lib\\tinyusb\\lib\\FreeRTOS-Kernel\\stream_buffer.c", "source_location": "L1365", "weight": 1.0}, {"source": "c_users_akrap_weather_station_lib_tinyusb_lib_freertos_kernel_stream_buffer_c", "target": "freertos_kernel_stream_buffer_prvreadbytesfrombuffer", "relation": "contains", "confidence": "EXTRACTED", "source_file": "C:\\Users\\akrap\\weather-station\\lib\\tinyusb\\lib\\FreeRTOS-Kernel\\stream_buffer.c", "source_location": "L1411", "weight": 1.0}, {"source": "c_users_akrap_weather_station_lib_tinyusb_lib_freertos_kernel_stream_buffer_c", "target": "freertos_kernel_stream_buffer_prvbytesinbuffer", "relation": "contains", "confidence": "EXTRACTED", "source_file": "C:\\Users\\akrap\\weather-station\\lib\\tinyusb\\lib\\FreeRTOS-Kernel\\stream_buffer.c", "source_location": "L1455", "weight": 1.0}, {"source": "c_users_akrap_weather_station_lib_tinyusb_lib_freertos_kernel_stream_buffer_c", "target": "freertos_kernel_stream_buffer_prvinitialisenewstreambuffer", "relation": "contains", "confidence": "EXTRACTED", "source_file": "C:\\Users\\akrap\\weather-station\\lib\\tinyusb\\lib\\FreeRTOS-Kernel\\stream_buffer.c", "source_location": "L1476", "weight": 1.0}, {"source": "c_users_akrap_weather_station_lib_tinyusb_lib_freertos_kernel_stream_buffer_c", "target": "freertos_kernel_stream_buffer_uxstreambuffergetstreambuffernumber", "relation": "contains", "confidence": "EXTRACTED", "source_file": "C:\\Users\\akrap\\weather-station\\lib\\tinyusb\\lib\\FreeRTOS-Kernel\\stream_buffer.c", "source_location": "L1524", "weight": 1.0}, {"source": "c_users_akrap_weather_station_lib_tinyusb_lib_freertos_kernel_stream_buffer_c", "target": "freertos_kernel_stream_buffer_vstreambuffersetstreambuffernumber", "relation": "contains", "confidence": "EXTRACTED", "source_file": "C:\\Users\\akrap\\weather-station\\lib\\tinyusb\\lib\\FreeRTOS-Kernel\\stream_buffer.c", "source_location": "L1538", "weight": 1.0}, {"source": "c_users_akrap_weather_station_lib_tinyusb_lib_freertos_kernel_stream_buffer_c", "target": "freertos_kernel_stream_buffer_ucstreambuffergetstreambuffertype", "relation": "contains", "confidence": "EXTRACTED", "source_file": "C:\\Users\\akrap\\weather-station\\lib\\tinyusb\\lib\\FreeRTOS-Kernel\\stream_buffer.c", "source_location": "L1553", "weight": 1.0}, {"source": "freertos_kernel_stream_buffer_xstreambuffergenericcreatestatic", "target": "freertos_kernel_stream_buffer_prvinitialisenewstreambuffer", "relation": "calls", "context": "call", "confidence": "EXTRACTED", "source_file": "C:\\Users\\akrap\\weather-station\\lib\\tinyusb\\lib\\FreeRTOS-Kernel\\stream_buffer.c", "source_location": "L466", "weight": 1.0}, {"source": "freertos_kernel_stream_buffer_xstreambufferreset", "target": "freertos_kernel_stream_buffer_prvinitialisenewstreambuffer", "relation": "calls", "context": "call", "confidence": "EXTRACTED", "source_file": "C:\\Users\\akrap\\weather-station\\lib\\tinyusb\\lib\\FreeRTOS-Kernel\\stream_buffer.c", "source_location": "L604", "weight": 1.0}, {"source": "freertos_kernel_stream_buffer_xstreambufferbytesavailable", "target": "freertos_kernel_stream_buffer_prvbytesinbuffer", "relation": "calls", "context": "call", "confidence": "EXTRACTED", "source_file": "C:\\Users\\akrap\\weather-station\\lib\\tinyusb\\lib\\FreeRTOS-Kernel\\stream_buffer.c", "source_location": "L711", "weight": 1.0}, {"source": "freertos_kernel_stream_buffer_xstreambuffersend", "target": "freertos_kernel_stream_buffer_xstreambufferspacesavailable", "relation": "calls", "context": "call", "confidence": "EXTRACTED", "source_file": "C:\\Users\\akrap\\weather-station\\lib\\tinyusb\\lib\\FreeRTOS-Kernel\\stream_buffer.c", "source_location": "L788", "weight": 1.0}, {"source": "freertos_kernel_stream_buffer_xstreambuffersend", "target": "freertos_kernel_stream_buffer_prvwritemessagetobuffer", "relation": "calls", "context": "call", "confidence": "EXTRACTED", "source_file": "C:\\Users\\akrap\\weather-station\\lib\\tinyusb\\lib\\FreeRTOS-Kernel\\stream_buffer.c", "source_location": "L826", "weight": 1.0}, {"source": "freertos_kernel_stream_buffer_xstreambuffersend", "target": "freertos_kernel_stream_buffer_prvbytesinbuffer", "relation": "calls", "context": "call", "confidence": "EXTRACTED", "source_file": "C:\\Users\\akrap\\weather-station\\lib\\tinyusb\\lib\\FreeRTOS-Kernel\\stream_buffer.c", "source_location": "L833", "weight": 1.0}, {"source": "freertos_kernel_stream_buffer_xstreambuffersendfromisr", "target": "freertos_kernel_stream_buffer_xstreambufferspacesavailable", "relation": "calls", "context": "call", "confidence": "EXTRACTED", "source_file": "C:\\Users\\akrap\\weather-station\\lib\\tinyusb\\lib\\FreeRTOS-Kernel\\stream_buffer.c", "source_location": "L881", "weight": 1.0}, {"source": "freertos_kernel_stream_buffer_xstreambuffersendfromisr", "target": "freertos_kernel_stream_buffer_prvwritemessagetobuffer", "relation": "calls", "context": "call", "confidence": "EXTRACTED", "source_file": "C:\\Users\\akrap\\weather-station\\lib\\tinyusb\\lib\\FreeRTOS-Kernel\\stream_buffer.c", "source_location": "L882", "weight": 1.0}, {"source": "freertos_kernel_stream_buffer_xstreambuffersendfromisr", "target": "freertos_kernel_stream_buffer_prvbytesinbuffer", "relation": "calls", "context": "call", "confidence": "EXTRACTED", "source_file": "C:\\Users\\akrap\\weather-station\\lib\\tinyusb\\lib\\FreeRTOS-Kernel\\stream_buffer.c", "source_location": "L887", "weight": 1.0}, {"source": "freertos_kernel_stream_buffer_prvwritemessagetobuffer", "target": "freertos_kernel_stream_buffer_prvwritebytestobuffer", "relation": "calls", "context": "call", "confidence": "EXTRACTED", "source_file": "C:\\Users\\akrap\\weather-station\\lib\\tinyusb\\lib\\FreeRTOS-Kernel\\stream_buffer.c", "source_location": "L932", "weight": 1.0}, {"source": "freertos_kernel_stream_buffer_xstreambufferreceive", "target": "freertos_kernel_stream_buffer_prvbytesinbuffer", "relation": "calls", "context": "call", "confidence": "EXTRACTED", "source_file": "C:\\Users\\akrap\\weather-station\\lib\\tinyusb\\lib\\FreeRTOS-Kernel\\stream_buffer.c", "source_location": "L994", "weight": 1.0}, {"source": "freertos_kernel_stream_buffer_xstreambufferreceive", "target": "freertos_kernel_stream_buffer_prvreadmessagefrombuffer", "relation": "calls", "context": "call", "confidence": "EXTRACTED", "source_file": "C:\\Users\\akrap\\weather-station\\lib\\tinyusb\\lib\\FreeRTOS-Kernel\\stream_buffer.c", "source_location": "L1044", "weight": 1.0}, {"source": "freertos_kernel_stream_buffer_xstreambuffernextmessagelengthbytes", "target": "freertos_kernel_stream_buffer_prvbytesinbuffer", "relation": "calls", "context": "call", "confidence": "EXTRACTED", "source_file": "C:\\Users\\akrap\\weather-station\\lib\\tinyusb\\lib\\FreeRTOS-Kernel\\stream_buffer.c", "source_location": "L1082", "weight": 1.0}, {"source": "freertos_kernel_stream_buffer_xstreambuffernextmessagelengthbytes", "target": "freertos_kernel_stream_buffer_prvreadbytesfrombuffer", "relation": "calls", "context": "call", "confidence": "EXTRACTED", "source_file": "C:\\Users\\akrap\\weather-station\\lib\\tinyusb\\lib\\FreeRTOS-Kernel\\stream_buffer.c", "source_location": "L1089", "weight": 1.0}, {"source": "freertos_kernel_stream_buffer_xstreambufferreceivefromisr", "target": "freertos_kernel_stream_buffer_prvbytesinbuffer", "relation": "calls", "context": "call", "confidence": "EXTRACTED", "source_file": "C:\\Users\\akrap\\weather-station\\lib\\tinyusb\\lib\\FreeRTOS-Kernel\\stream_buffer.c", "source_location": "L1140", "weight": 1.0}, {"source": "freertos_kernel_stream_buffer_xstreambufferreceivefromisr", "target": "freertos_kernel_stream_buffer_prvreadmessagefrombuffer", "relation": "calls", "context": "call", "confidence": "EXTRACTED", "source_file": "C:\\Users\\akrap\\weather-station\\lib\\tinyusb\\lib\\FreeRTOS-Kernel\\stream_buffer.c", "source_location": "L1149", "weight": 1.0}, {"source": "freertos_kernel_stream_buffer_prvreadmessagefrombuffer", "target": "freertos_kernel_stream_buffer_prvreadbytesfrombuffer", "relation": "calls", "context": "call", "confidence": "EXTRACTED", "source_file": "C:\\Users\\akrap\\weather-station\\lib\\tinyusb\\lib\\FreeRTOS-Kernel\\stream_buffer.c", "source_location": "L1186", "weight": 1.0}, {"source": "freertos_kernel_stream_buffer_xstreambufferisfull", "target": "freertos_kernel_stream_buffer_xstreambufferspacesavailable", "relation": "calls", "context": "call", "confidence": "EXTRACTED", "source_file": "C:\\Users\\akrap\\weather-station\\lib\\tinyusb\\lib\\FreeRTOS-Kernel\\stream_buffer.c", "source_location": "L1280", "weight": 1.0}], "raw_calls": [{"caller_nid": "freertos_kernel_stream_buffer_prvinitialisenewstreambuffer", "callee": "configASSERT", "is_member_call": false, "source_file": "C:\\Users\\akrap\\weather-station\\lib\\tinyusb\\lib\\FreeRTOS-Kernel\\stream_buffer.c", "source_location": "L338"}, {"caller_nid": "freertos_kernel_stream_buffer_xstreambuffergenericcreatestatic", "callee": "traceENTER_xStreamBufferGenericCreateStatic", "is_member_call": false, "source_file": "C:\\Users\\akrap\\weather-station\\lib\\tinyusb\\lib\\FreeRTOS-Kernel\\stream_buffer.c", "source_location": "L424"}, {"caller_nid": "freertos_kernel_stream_buffer_xstreambuffergenericcreatestatic", "callee": "configASSERT", "is_member_call": false, "source_file": "C:\\Users\\akrap\\weather-station\\lib\\tinyusb\\lib\\FreeRTOS-Kernel\\stream_buffer.c", "source_location": "L426"}, {"caller_nid": "freertos_kernel_stream_buffer_xstreambuffergenericcreatestatic", "callee": "configASSERT", "is_member_call": false, "source_file": "C:\\Users\\akrap\\weather-station\\lib\\tinyusb\\lib\\FreeRTOS-Kernel\\stream_buffer.c", "source_location": "L427"}, {"caller_nid": "freertos_kernel_stream_buffer_xstreambuffergenericcreatestatic", "callee": "configASSERT", "is_member_call": false, "source_file": "C:\\Users\\akrap\\weather-station\\lib\\tinyusb\\lib\\FreeRTOS-Kernel\\stream_buffer.c", "source_location": "L428"}, {"caller_nid": "freertos_kernel_stream_buffer_xstreambuffergenericcreatestatic", "callee": "configASSERT", "is_member_call": false, "source_file": "C:\\Users\\akrap\\weather-station\\lib\\tinyusb\\lib\\FreeRTOS-Kernel\\stream_buffer.c", "source_location": "L446"}, {"caller_nid": "freertos_kernel_stream_buffer_xstreambuffergenericcreatestatic", "callee": "configASSERT", "is_member_call": false, "source_file": "C:\\Users\\akrap\\weather-station\\lib\\tinyusb\\lib\\FreeRTOS-Kernel\\stream_buffer.c", "source_location": "L460"}, {"caller_nid": "freertos_kernel_stream_buffer_xstreambuffergenericcreatestatic", "callee": "traceSTREAM_BUFFER_CREATE", "is_member_call": false, "source_file": "C:\\Users\\akrap\\weather-station\\lib\\tinyusb\\lib\\FreeRTOS-Kernel\\stream_buffer.c", "source_location": "L478"}, {"caller_nid": "freertos_kernel_stream_buffer_xstreambuffergenericcreatestatic", "callee": "traceSTREAM_BUFFER_CREATE_STATIC_FAILED", "is_member_call": false, "source_file": "C:\\Users\\akrap\\weather-station\\lib\\tinyusb\\lib\\FreeRTOS-Kernel\\stream_buffer.c", "source_location": "L488"}, {"caller_nid": "freertos_kernel_stream_buffer_xstreambuffergenericcreatestatic", "callee": "traceRETURN_xStreamBufferGenericCreateStatic", "is_member_call": false, "source_file": "C:\\Users\\akrap\\weather-station\\lib\\tinyusb\\lib\\FreeRTOS-Kernel\\stream_buffer.c", "source_location": "L491"}, {"caller_nid": "freertos_kernel_stream_buffer_xstreambuffergetstaticbuffers", "callee": "traceENTER_xStreamBufferGetStaticBuffers", "is_member_call": false, "source_file": "C:\\Users\\akrap\\weather-station\\lib\\tinyusb\\lib\\FreeRTOS-Kernel\\stream_buffer.c", "source_location": "L506"}, {"caller_nid": "freertos_kernel_stream_buffer_xstreambuffergetstaticbuffers", "callee": "configASSERT", "is_member_call": false, "source_file": "C:\\Users\\akrap\\weather-station\\lib\\tinyusb\\lib\\FreeRTOS-Kernel\\stream_buffer.c", "source_location": "L508"}, {"caller_nid": "freertos_kernel_stream_buffer_xstreambuffergetstaticbuffers", "callee": "configASSERT", "is_member_call": false, "source_file": "C:\\Users\\akrap\\weather-station\\lib\\tinyusb\\lib\\FreeRTOS-Kernel\\stream_buffer.c", "source_location": "L509"}, {"caller_nid": "freertos_kernel_stream_buffer_xstreambuffergetstaticbuffers", "callee": "configASSERT", "is_member_call": false, "source_file": "C:\\Users\\akrap\\weather-station\\lib\\tinyusb\\lib\\FreeRTOS-Kernel\\stream_buffer.c", "source_location": "L510"}, {"caller_nid": "freertos_kernel_stream_buffer_xstreambuffergetstaticbuffers", "callee": "traceRETURN_xStreamBufferGetStaticBuffers", "is_member_call": false, "source_file": "C:\\Users\\akrap\\weather-station\\lib\\tinyusb\\lib\\FreeRTOS-Kernel\\stream_buffer.c", "source_location": "L526"}, {"caller_nid": "freertos_kernel_stream_buffer_vstreambufferdelete", "callee": "traceENTER_vStreamBufferDelete", "is_member_call": false, "source_file": "C:\\Users\\akrap\\weather-station\\lib\\tinyusb\\lib\\FreeRTOS-Kernel\\stream_buffer.c", "source_location": "L537"}, {"caller_nid": "freertos_kernel_stream_buffer_vstreambufferdelete", "callee": "configASSERT", "is_member_call": false, "source_file": "C:\\Users\\akrap\\weather-station\\lib\\tinyusb\\lib\\FreeRTOS-Kernel\\stream_buffer.c", "source_location": "L539"}, {"caller_nid": "freertos_kernel_stream_buffer_vstreambufferdelete", "callee": "traceSTREAM_BUFFER_DELETE", "is_member_call": false, "source_file": "C:\\Users\\akrap\\weather-station\\lib\\tinyusb\\lib\\FreeRTOS-Kernel\\stream_buffer.c", "source_location": "L541"}, {"caller_nid": "freertos_kernel_stream_buffer_vstreambufferdelete", "callee": "vPortFree", "is_member_call": false, "source_file": "C:\\Users\\akrap\\weather-station\\lib\\tinyusb\\lib\\FreeRTOS-Kernel\\stream_buffer.c", "source_location": "L549"}, {"caller_nid": "freertos_kernel_stream_buffer_vstreambufferdelete", "callee": "configASSERT", "is_member_call": false, "source_file": "C:\\Users\\akrap\\weather-station\\lib\\tinyusb\\lib\\FreeRTOS-Kernel\\stream_buffer.c", "source_location": "L555"}, {"caller_nid": "freertos_kernel_stream_buffer_vstreambufferdelete", "callee": "memset", "is_member_call": false, "source_file": "C:\\Users\\akrap\\weather-station\\lib\\tinyusb\\lib\\FreeRTOS-Kernel\\stream_buffer.c", "source_location": "L563"}, {"caller_nid": "freertos_kernel_stream_buffer_vstreambufferdelete", "callee": "traceRETURN_vStreamBufferDelete", "is_member_call": false, "source_file": "C:\\Users\\akrap\\weather-station\\lib\\tinyusb\\lib\\FreeRTOS-Kernel\\stream_buffer.c", "source_location": "L566"}, {"caller_nid": "freertos_kernel_stream_buffer_xstreambufferreset", "callee": "traceENTER_xStreamBufferReset", "is_member_call": false, "source_file": "C:\\Users\\akrap\\weather-station\\lib\\tinyusb\\lib\\FreeRTOS-Kernel\\stream_buffer.c", "source_location": "L580"}, {"caller_nid": "freertos_kernel_stream_buffer_xstreambufferreset", "callee": "configASSERT", "is_member_call": false, "source_file": "C:\\Users\\akrap\\weather-station\\lib\\tinyusb\\lib\\FreeRTOS-Kernel\\stream_buffer.c", "source_location": "L582"}, {"caller_nid": "freertos_kernel_stream_buffer_xstreambufferreset", "callee": "taskENTER_CRITICAL", "is_member_call": false, "source_file": "C:\\Users\\akrap\\weather-station\\lib\\tinyusb\\lib\\FreeRTOS-Kernel\\stream_buffer.c", "source_location": "L593"}, {"caller_nid": "freertos_kernel_stream_buffer_xstreambufferreset", "callee": "traceSTREAM_BUFFER_RESET", "is_member_call": false, "source_file": "C:\\Users\\akrap\\weather-station\\lib\\tinyusb\\lib\\FreeRTOS-Kernel\\stream_buffer.c", "source_location": "L618"}, {"caller_nid": "freertos_kernel_stream_buffer_xstreambufferreset", "callee": "taskEXIT_CRITICAL", "is_member_call": false, "source_file": "C:\\Users\\akrap\\weather-station\\lib\\tinyusb\\lib\\FreeRTOS-Kernel\\stream_buffer.c", "source_location": "L623"}, {"caller_nid": "freertos_kernel_stream_buffer_xstreambufferreset", "callee": "traceRETURN_xStreamBufferReset", "is_member_call": false, "source_file": "C:\\Users\\akrap\\weather-station\\lib\\tinyusb\\lib\\FreeRTOS-Kernel\\stream_buffer.c", "source_location": "L625"}, {"caller_nid": "freertos_kernel_stream_buffer_xstreambuffersettriggerlevel", "callee": "traceENTER_xStreamBufferSetTriggerLevel", "is_member_call": false, "source_file": "C:\\Users\\akrap\\weather-station\\lib\\tinyusb\\lib\\FreeRTOS-Kernel\\stream_buffer.c", "source_location": "L637"}, {"caller_nid": "freertos_kernel_stream_buffer_xstreambuffersettriggerlevel", "callee": "configASSERT", "is_member_call": false, "source_file": "C:\\Users\\akrap\\weather-station\\lib\\tinyusb\\lib\\FreeRTOS-Kernel\\stream_buffer.c", "source_location": "L639"}, {"caller_nid": "freertos_kernel_stream_buffer_xstreambuffersettriggerlevel", "callee": "traceRETURN_xStreamBufferSetTriggerLevel", "is_member_call": false, "source_file": "C:\\Users\\akrap\\weather-station\\lib\\tinyusb\\lib\\FreeRTOS-Kernel\\stream_buffer.c", "source_location": "L659"}, {"caller_nid": "freertos_kernel_stream_buffer_xstreambufferspacesavailable", "callee": "traceENTER_xStreamBufferSpacesAvailable", "is_member_call": false, "source_file": "C:\\Users\\akrap\\weather-station\\lib\\tinyusb\\lib\\FreeRTOS-Kernel\\stream_buffer.c", "source_location": "L671"}, {"caller_nid": "freertos_kernel_stream_buffer_xstreambufferspacesavailable", "callee": "configASSERT", "is_member_call": false, "source_file": "C:\\Users\\akrap\\weather-station\\lib\\tinyusb\\lib\\FreeRTOS-Kernel\\stream_buffer.c", "source_location": "L673"}, {"caller_nid": "freertos_kernel_stream_buffer_xstreambufferspacesavailable", "callee": "mtCOVERAGE_TEST_MARKER", "is_member_call": false, "source_file": "C:\\Users\\akrap\\weather-station\\lib\\tinyusb\\lib\\FreeRTOS-Kernel\\stream_buffer.c", "source_location": "L693"}, {"caller_nid": "freertos_kernel_stream_buffer_xstreambufferspacesavailable", "callee": "traceRETURN_xStreamBufferSpacesAvailable", "is_member_call": false, "source_file": "C:\\Users\\akrap\\weather-station\\lib\\tinyusb\\lib\\FreeRTOS-Kernel\\stream_buffer.c", "source_location": "L696"}, {"caller_nid": "freertos_kernel_stream_buffer_xstreambufferbytesavailable", "callee": "traceENTER_xStreamBufferBytesAvailable", "is_member_call": false, "source_file": "C:\\Users\\akrap\\weather-station\\lib\\tinyusb\\lib\\FreeRTOS-Kernel\\stream_buffer.c", "source_location": "L707"}, {"caller_nid": "freertos_kernel_stream_buffer_xstreambufferbytesavailable", "callee": "configASSERT", "is_member_call": false, "source_file": "C:\\Users\\akrap\\weather-station\\lib\\tinyusb\\lib\\FreeRTOS-Kernel\\stream_buffer.c", "source_location": "L709"}, {"caller_nid": "freertos_kernel_stream_buffer_xstreambufferbytesavailable", "callee": "traceRETURN_xStreamBufferBytesAvailable", "is_member_call": false, "source_file": "C:\\Users\\akrap\\weather-station\\lib\\tinyusb\\lib\\FreeRTOS-Kernel\\stream_buffer.c", "source_location": "L713"}, {"caller_nid": "freertos_kernel_stream_buffer_xstreambuffersend", "callee": "traceENTER_xStreamBufferSend", "is_member_call": false, "source_file": "C:\\Users\\akrap\\weather-station\\lib\\tinyusb\\lib\\FreeRTOS-Kernel\\stream_buffer.c", "source_location": "L730"}, {"caller_nid": "freertos_kernel_stream_buffer_xstreambuffersend", "callee": "configASSERT", "is_member_call": false, "source_file": "C:\\Users\\akrap\\weather-station\\lib\\tinyusb\\lib\\FreeRTOS-Kernel\\stream_buffer.c", "source_location": "L732"}, {"caller_nid": "freertos_kernel_stream_buffer_xstreambuffersend", "callee": "configASSERT", "is_member_call": false, "source_file": "C:\\Users\\akrap\\weather-station\\lib\\tinyusb\\lib\\FreeRTOS-Kernel\\stream_buffer.c", "source_location": "L733"}, {"caller_nid": "freertos_kernel_stream_buffer_xstreambuffersend", "callee": "configASSERT", "is_member_call": false, "source_file": "C:\\Users\\akrap\\weather-station\\lib\\tinyusb\\lib\\FreeRTOS-Kernel\\stream_buffer.c", "source_location": "L748"}, {"caller_nid": "freertos_kernel_stream_buffer_xstreambuffersend", "callee": "mtCOVERAGE_TEST_MARKER", "is_member_call": false, "source_file": "C:\\Users\\akrap\\weather-station\\lib\\tinyusb\\lib\\FreeRTOS-Kernel\\stream_buffer.c", "source_location": "L760"}, {"caller_nid": "freertos_kernel_stream_buffer_xstreambuffersend", "callee": "mtCOVERAGE_TEST_MARKER", "is_member_call": false, "source_file": "C:\\Users\\akrap\\weather-station\\lib\\tinyusb\\lib\\FreeRTOS-Kernel\\stream_buffer.c", "source_location": "L774"}, {"caller_nid": "freertos_kernel_stream_buffer_xstreambuffersend", "callee": "vTaskSetTimeOutState", "is_member_call": false, "source_file": "C:\\Users\\akrap\\weather-station\\lib\\tinyusb\\lib\\FreeRTOS-Kernel\\stream_buffer.c", "source_location": "L780"}, {"caller_nid": "freertos_kernel_stream_buffer_xstreambuffersend", "callee": "taskENTER_CRITICAL", "is_member_call": false, "source_file": "C:\\Users\\akrap\\weather-station\\lib\\tinyusb\\lib\\FreeRTOS-Kernel\\stream_buffer.c", "source_location": "L786"}, {"caller_nid": "freertos_kernel_stream_buffer_xstreambuffersend", "callee": "xTaskNotifyStateClear", "is_member_call": false, "source_file": "C:\\Users\\akrap\\weather-station\\lib\\tinyusb\\lib\\FreeRTOS-Kernel\\stream_buffer.c", "source_location": "L793"}, {"caller_nid": "freertos_kernel_stream_buffer_xstreambuffersend", "callee": "configASSERT", "is_member_call": false, "source_file": "C:\\Users\\akrap\\weather-station\\lib\\tinyusb\\lib\\FreeRTOS-Kernel\\stream_buffer.c", "source_location": "L796"}, {"caller_nid": "freertos_kernel_stream_buffer_xstreambuffersend", "callee": "xTaskGetCurrentTaskHandle", "is_member_call": false, "source_file": "C:\\Users\\akrap\\weather-station\\lib\\tinyusb\\lib\\FreeRTOS-Kernel\\stream_buffer.c", "source_location": "L797"}, {"caller_nid": "freertos_kernel_stream_buffer_xstreambuffersend", "callee": "taskEXIT_CRITICAL", "is_member_call": false, "source_file": "C:\\Users\\akrap\\weather-station\\lib\\tinyusb\\lib\\FreeRTOS-Kernel\\stream_buffer.c", "source_location": "L801"}, {"caller_nid": "freertos_kernel_stream_buffer_xstreambuffersend", "callee": "taskEXIT_CRITICAL", "is_member_call": false, "source_file": "C:\\Users\\akrap\\weather-station\\lib\\tinyusb\\lib\\FreeRTOS-Kernel\\stream_buffer.c", "source_location": "L805"}, {"caller_nid": "freertos_kernel_stream_buffer_xstreambuffersend", "callee": "traceBLOCKING_ON_STREAM_BUFFER_SEND", "is_member_call": false, "source_file": "C:\\Users\\akrap\\weather-station\\lib\\tinyusb\\lib\\FreeRTOS-Kernel\\stream_buffer.c", "source_location": "L807"}, {"caller_nid": "freertos_kernel_stream_buffer_xstreambuffersend", "callee": "xTaskNotifyWait", "is_member_call": false, "source_file": "C:\\Users\\akrap\\weather-station\\lib\\tinyusb\\lib\\FreeRTOS-Kernel\\stream_buffer.c", "source_location": "L808"}, {"caller_nid": "freertos_kernel_stream_buffer_xstreambuffersend", "callee": "xTaskCheckForTimeOut", "is_member_call": false, "source_file": "C:\\Users\\akrap\\weather-station\\lib\\tinyusb\\lib\\FreeRTOS-Kernel\\stream_buffer.c", "source_location": "L810"}, {"caller_nid": "freertos_kernel_stream_buffer_xstreambuffersend", "callee": "mtCOVERAGE_TEST_MARKER", "is_member_call": false, "source_file": "C:\\Users\\akrap\\weather-station\\lib\\tinyusb\\lib\\FreeRTOS-Kernel\\stream_buffer.c", "source_location": "L814"}, {"caller_nid": "freertos_kernel_stream_buffer_xstreambuffersend", "callee": "mtCOVERAGE_TEST_MARKER", "is_member_call": false, "source_file": "C:\\Users\\akrap\\weather-station\\lib\\tinyusb\\lib\\FreeRTOS-Kernel\\stream_buffer.c", "source_location": "L823"}, {"caller_nid": "freertos_kernel_stream_buffer_xstreambuffersend", "callee": "traceSTREAM_BUFFER_SEND", "is_member_call": false, "source_file": "C:\\Users\\akrap\\weather-station\\lib\\tinyusb\\lib\\FreeRTOS-Kernel\\stream_buffer.c", "source_location": "L830"}, {"caller_nid": "freertos_kernel_stream_buffer_xstreambuffersend", "callee": "prvSEND_COMPLETED", "is_member_call": false, "source_file": "C:\\Users\\akrap\\weather-station\\lib\\tinyusb\\lib\\FreeRTOS-Kernel\\stream_buffer.c", "source_location": "L835"}, {"caller_nid": "freertos_kernel_stream_buffer_xstreambuffersend", "callee": "mtCOVERAGE_TEST_MARKER", "is_member_call": false, "source_file": "C:\\Users\\akrap\\weather-station\\lib\\tinyusb\\lib\\FreeRTOS-Kernel\\stream_buffer.c", "source_location": "L839"}, {"caller_nid": "freertos_kernel_stream_buffer_xstreambuffersend", "callee": "mtCOVERAGE_TEST_MARKER", "is_member_call": false, "source_file": "C:\\Users\\akrap\\weather-station\\lib\\tinyusb\\lib\\FreeRTOS-Kernel\\stream_buffer.c", "source_location": "L844"}, {"caller_nid": "freertos_kernel_stream_buffer_xstreambuffersend", "callee": "traceSTREAM_BUFFER_SEND_FAILED", "is_member_call": false, "source_file": "C:\\Users\\akrap\\weather-station\\lib\\tinyusb\\lib\\FreeRTOS-Kernel\\stream_buffer.c", "source_location": "L845"}, {"caller_nid": "freertos_kernel_stream_buffer_xstreambuffersend", "callee": "traceRETURN_xStreamBufferSend", "is_member_call": false, "source_file": "C:\\Users\\akrap\\weather-station\\lib\\tinyusb\\lib\\FreeRTOS-Kernel\\stream_buffer.c", "source_location": "L848"}, {"caller_nid": "freertos_kernel_stream_buffer_xstreambuffersendfromisr", "callee": "traceENTER_xStreamBufferSendFromISR", "is_member_call": false, "source_file": "C:\\Users\\akrap\\weather-station\\lib\\tinyusb\\lib\\FreeRTOS-Kernel\\stream_buffer.c", "source_location": "L863"}, {"caller_nid": "freertos_kernel_stream_buffer_xstreambuffersendfromisr", "callee": "configASSERT", "is_member_call": false, "source_file": "C:\\Users\\akrap\\weather-station\\lib\\tinyusb\\lib\\FreeRTOS-Kernel\\stream_buffer.c", "source_location": "L865"}, {"caller_nid": "freertos_kernel_stream_buffer_xstreambuffersendfromisr", "callee": "configASSERT", "is_member_call": false, "source_file": "C:\\Users\\akrap\\weather-station\\lib\\tinyusb\\lib\\FreeRTOS-Kernel\\stream_buffer.c", "source_location": "L866"}, {"caller_nid": "freertos_kernel_stream_buffer_xstreambuffersendfromisr", "callee": "mtCOVERAGE_TEST_MARKER", "is_member_call": false, "source_file": "C:\\Users\\akrap\\weather-station\\lib\\tinyusb\\lib\\FreeRTOS-Kernel\\stream_buffer.c", "source_location": "L878"}, {"caller_nid": "freertos_kernel_stream_buffer_xstreambuffersendfromisr", "callee": "prvSEND_COMPLETE_FROM_ISR", "is_member_call": false, "source_file": "C:\\Users\\akrap\\weather-station\\lib\\tinyusb\\lib\\FreeRTOS-Kernel\\stream_buffer.c", "source_location": "L889"}, {"caller_nid": "freertos_kernel_stream_buffer_xstreambuffersendfromisr", "callee": "mtCOVERAGE_TEST_MARKER", "is_member_call": false, "source_file": "C:\\Users\\akrap\\weather-station\\lib\\tinyusb\\lib\\FreeRTOS-Kernel\\stream_buffer.c", "source_location": "L893"}, {"caller_nid": "freertos_kernel_stream_buffer_xstreambuffersendfromisr", "callee": "mtCOVERAGE_TEST_MARKER", "is_member_call": false, "source_file": "C:\\Users\\akrap\\weather-station\\lib\\tinyusb\\lib\\FreeRTOS-Kernel\\stream_buffer.c", "source_location": "L898"}, {"caller_nid": "freertos_kernel_stream_buffer_xstreambuffersendfromisr", "callee": "traceSTREAM_BUFFER_SEND_FROM_ISR", "is_member_call": false, "source_file": "C:\\Users\\akrap\\weather-station\\lib\\tinyusb\\lib\\FreeRTOS-Kernel\\stream_buffer.c", "source_location": "L901"}, {"caller_nid": "freertos_kernel_stream_buffer_xstreambuffersendfromisr", "callee": "traceRETURN_xStreamBufferSendFromISR", "is_member_call": false, "source_file": "C:\\Users\\akrap\\weather-station\\lib\\tinyusb\\lib\\FreeRTOS-Kernel\\stream_buffer.c", "source_location": "L902"}, {"caller_nid": "freertos_kernel_stream_buffer_prvwritemessagetobuffer", "callee": "configASSERT", "is_member_call": false, "source_file": "C:\\Users\\akrap\\weather-station\\lib\\tinyusb\\lib\\FreeRTOS-Kernel\\stream_buffer.c", "source_location": "L925"}, {"caller_nid": "freertos_kernel_stream_buffer_prvwritemessagetobuffer", "callee": "configMIN", "is_member_call": false, "source_file": "C:\\Users\\akrap\\weather-station\\lib\\tinyusb\\lib\\FreeRTOS-Kernel\\stream_buffer.c", "source_location": "L945"}, {"caller_nid": "freertos_kernel_stream_buffer_xstreambufferreceive", "callee": "traceENTER_xStreamBufferReceive", "is_member_call": false, "source_file": "C:\\Users\\akrap\\weather-station\\lib\\tinyusb\\lib\\FreeRTOS-Kernel\\stream_buffer.c", "source_location": "L969"}, {"caller_nid": "freertos_kernel_stream_buffer_xstreambufferreceive", "callee": "configASSERT", "is_member_call": false, "source_file": "C:\\Users\\akrap\\weather-station\\lib\\tinyusb\\lib\\FreeRTOS-Kernel\\stream_buffer.c", "source_location": "L971"}, {"caller_nid": "freertos_kernel_stream_buffer_xstreambufferreceive", "callee": "configASSERT", "is_member_call": false, "source_file": "C:\\Users\\akrap\\weather-station\\lib\\tinyusb\\lib\\FreeRTOS-Kernel\\stream_buffer.c", "source_location": "L972"}, {"caller_nid": "freertos_kernel_stream_buffer_xstreambufferreceive", "callee": "taskENTER_CRITICAL", "is_member_call": false, "source_file": "C:\\Users\\akrap\\weather-station\\lib\\tinyusb\\lib\\FreeRTOS-Kernel\\stream_buffer.c", "source_location": "L992"}, {"caller_nid": "freertos_kernel_stream_buffer_xstreambufferreceive", "callee": "xTaskNotifyStateClear", "is_member_call": false, "source_file": "C:\\Users\\akrap\\weather-station\\lib\\tinyusb\\lib\\FreeRTOS-Kernel\\stream_buffer.c", "source_location": "L1004"}, {"caller_nid": "freertos_kernel_stream_buffer_xstreambufferreceive", "callee": "configASSERT", "is_member_call": false, "source_file": "C:\\Users\\akrap\\weather-station\\lib\\tinyusb\\lib\\FreeRTOS-Kernel\\stream_buffer.c", "source_location": "L1007"}, {"caller_nid": "freertos_kernel_stream_buffer_xstreambufferreceive", "callee": "xTaskGetCurrentTaskHandle", "is_member_call": false, "source_file": "C:\\Users\\akrap\\weather-station\\lib\\tinyusb\\lib\\FreeRTOS-Kernel\\stream_buffer.c", "source_location": "L1008"}, {"caller_nid": "freertos_kernel_stream_buffer_xstreambufferreceive", "callee": "mtCOVERAGE_TEST_MARKER", "is_member_call": false, "source_file": "C:\\Users\\akrap\\weather-station\\lib\\tinyusb\\lib\\FreeRTOS-Kernel\\stream_buffer.c", "source_location": "L1012"}, {"caller_nid": "freertos_kernel_stream_buffer_xstreambufferreceive", "callee": "taskEXIT_CRITICAL", "is_member_call": false, "source_file": "C:\\Users\\akrap\\weather-station\\lib\\tinyusb\\lib\\FreeRTOS-Kernel\\stream_buffer.c", "source_location": "L1015"}, {"caller_nid": "freertos_kernel_stream_buffer_xstreambufferreceive", "callee": "traceBLOCKING_ON_STREAM_BUFFER_RECEIVE", "is_member_call": false, "source_file": "C:\\Users\\akrap\\weather-station\\lib\\tinyusb\\lib\\FreeRTOS-Kernel\\stream_buffer.c", "source_location": "L1020"}, {"caller_nid": "freertos_kernel_stream_buffer_xstreambufferreceive", "callee": "xTaskNotifyWait", "is_member_call": false, "source_file": "C:\\Users\\akrap\\weather-station\\lib\\tinyusb\\lib\\FreeRTOS-Kernel\\stream_buffer.c", "source_location": "L1021"}, {"caller_nid": "freertos_kernel_stream_buffer_xstreambufferreceive", "callee": "mtCOVERAGE_TEST_MARKER", "is_member_call": false, "source_file": "C:\\Users\\akrap\\weather-station\\lib\\tinyusb\\lib\\FreeRTOS-Kernel\\stream_buffer.c", "source_location": "L1029"}, {"caller_nid": "freertos_kernel_stream_buffer_xstreambufferreceive", "callee": "traceSTREAM_BUFFER_RECEIVE", "is_member_call": false, "source_file": "C:\\Users\\akrap\\weather-station\\lib\\tinyusb\\lib\\FreeRTOS-Kernel\\stream_buffer.c", "source_location": "L1049"}, {"caller_nid": "freertos_kernel_stream_buffer_xstreambufferreceive", "callee": "prvRECEIVE_COMPLETED", "is_member_call": false, "source_file": "C:\\Users\\akrap\\weather-station\\lib\\tinyusb\\lib\\FreeRTOS-Kernel\\stream_buffer.c", "source_location": "L1050"}, {"caller_nid": "freertos_kernel_stream_buffer_xstreambufferreceive", "callee": "mtCOVERAGE_TEST_MARKER", "is_member_call": false, "source_file": "C:\\Users\\akrap\\weather-station\\lib\\tinyusb\\lib\\FreeRTOS-Kernel\\stream_buffer.c", "source_location": "L1054"}, {"caller_nid": "freertos_kernel_stream_buffer_xstreambufferreceive", "callee": "traceSTREAM_BUFFER_RECEIVE_FAILED", "is_member_call": false, "source_file": "C:\\Users\\akrap\\weather-station\\lib\\tinyusb\\lib\\FreeRTOS-Kernel\\stream_buffer.c", "source_location": "L1059"}, {"caller_nid": "freertos_kernel_stream_buffer_xstreambufferreceive", "callee": "mtCOVERAGE_TEST_MARKER", "is_member_call": false, "source_file": "C:\\Users\\akrap\\weather-station\\lib\\tinyusb\\lib\\FreeRTOS-Kernel\\stream_buffer.c", "source_location": "L1060"}, {"caller_nid": "freertos_kernel_stream_buffer_xstreambufferreceive", "callee": "traceRETURN_xStreamBufferReceive", "is_member_call": false, "source_file": "C:\\Users\\akrap\\weather-station\\lib\\tinyusb\\lib\\FreeRTOS-Kernel\\stream_buffer.c", "source_location": "L1063"}, {"caller_nid": "freertos_kernel_stream_buffer_xstreambuffernextmessagelengthbytes", "callee": "traceENTER_xStreamBufferNextMessageLengthBytes", "is_member_call": false, "source_file": "C:\\Users\\akrap\\weather-station\\lib\\tinyusb\\lib\\FreeRTOS-Kernel\\stream_buffer.c", "source_location": "L1075"}, {"caller_nid": "freertos_kernel_stream_buffer_xstreambuffernextmessagelengthbytes", "callee": "configASSERT", "is_member_call": false, "source_file": "C:\\Users\\akrap\\weather-station\\lib\\tinyusb\\lib\\FreeRTOS-Kernel\\stream_buffer.c", "source_location": "L1077"}, {"caller_nid": "freertos_kernel_stream_buffer_xstreambuffernextmessagelengthbytes", "callee": "configASSERT", "is_member_call": false, "source_file": "C:\\Users\\akrap\\weather-station\\lib\\tinyusb\\lib\\FreeRTOS-Kernel\\stream_buffer.c", "source_location": "L1098"}, {"caller_nid": "freertos_kernel_stream_buffer_xstreambuffernextmessagelengthbytes", "callee": "traceRETURN_xStreamBufferNextMessageLengthBytes", "is_member_call": false, "source_file": "C:\\Users\\akrap\\weather-station\\lib\\tinyusb\\lib\\FreeRTOS-Kernel\\stream_buffer.c", "source_location": "L1107"}, {"caller_nid": "freertos_kernel_stream_buffer_xstreambufferreceivefromisr", "callee": "traceENTER_xStreamBufferReceiveFromISR", "is_member_call": false, "source_file": "C:\\Users\\akrap\\weather-station\\lib\\tinyusb\\lib\\FreeRTOS-Kernel\\stream_buffer.c", "source_location": "L1121"}, {"caller_nid": "freertos_kernel_stream_buffer_xstreambufferreceivefromisr", "callee": "configASSERT", "is_member_call": false, "source_file": "C:\\Users\\akrap\\weather-station\\lib\\tinyusb\\lib\\FreeRTOS-Kernel\\stream_buffer.c", "source_location": "L1123"}, {"caller_nid": "freertos_kernel_stream_buffer_xstreambufferreceivefromisr", "callee": "configASSERT", "is_member_call": false, "source_file": "C:\\Users\\akrap\\weather-station\\lib\\tinyusb\\lib\\FreeRTOS-Kernel\\stream_buffer.c", "source_location": "L1124"}, {"caller_nid": "freertos_kernel_stream_buffer_xstreambufferreceivefromisr", "callee": "prvRECEIVE_COMPLETED_FROM_ISR", "is_member_call": false, "source_file": "C:\\Users\\akrap\\weather-station\\lib\\tinyusb\\lib\\FreeRTOS-Kernel\\stream_buffer.c", "source_location": "L1154"}, {"caller_nid": "freertos_kernel_stream_buffer_xstreambufferreceivefromisr", "callee": "mtCOVERAGE_TEST_MARKER", "is_member_call": false, "source_file": "C:\\Users\\akrap\\weather-station\\lib\\tinyusb\\lib\\FreeRTOS-Kernel\\stream_buffer.c", "source_location": "L1158"}, {"caller_nid": "freertos_kernel_stream_buffer_xstreambufferreceivefromisr", "callee": "mtCOVERAGE_TEST_MARKER", "is_member_call": false, "source_file": "C:\\Users\\akrap\\weather-station\\lib\\tinyusb\\lib\\FreeRTOS-Kernel\\stream_buffer.c", "source_location": "L1163"}, {"caller_nid": "freertos_kernel_stream_buffer_xstreambufferreceivefromisr", "callee": "traceSTREAM_BUFFER_RECEIVE_FROM_ISR", "is_member_call": false, "source_file": "C:\\Users\\akrap\\weather-station\\lib\\tinyusb\\lib\\FreeRTOS-Kernel\\stream_buffer.c", "source_location": "L1166"}, {"caller_nid": "freertos_kernel_stream_buffer_xstreambufferreceivefromisr", "callee": "traceRETURN_xStreamBufferReceiveFromISR", "is_member_call": false, "source_file": "C:\\Users\\akrap\\weather-station\\lib\\tinyusb\\lib\\FreeRTOS-Kernel\\stream_buffer.c", "source_location": "L1167"}, {"caller_nid": "freertos_kernel_stream_buffer_prvreadmessagefrombuffer", "callee": "mtCOVERAGE_TEST_MARKER", "is_member_call": false, "source_file": "C:\\Users\\akrap\\weather-station\\lib\\tinyusb\\lib\\FreeRTOS-Kernel\\stream_buffer.c", "source_location": "L1202"}, {"caller_nid": "freertos_kernel_stream_buffer_prvreadmessagefrombuffer", "callee": "configMIN", "is_member_call": false, "source_file": "C:\\Users\\akrap\\weather-station\\lib\\tinyusb\\lib\\FreeRTOS-Kernel\\stream_buffer.c", "source_location": "L1213"}, {"caller_nid": "freertos_kernel_stream_buffer_xstreambufferisempty", "callee": "traceENTER_xStreamBufferIsEmpty", "is_member_call": false, "source_file": "C:\\Users\\akrap\\weather-station\\lib\\tinyusb\\lib\\FreeRTOS-Kernel\\stream_buffer.c", "source_location": "L1234"}, {"caller_nid": "freertos_kernel_stream_buffer_xstreambufferisempty", "callee": "configASSERT", "is_member_call": false, "source_file": "C:\\Users\\akrap\\weather-station\\lib\\tinyusb\\lib\\FreeRTOS-Kernel\\stream_buffer.c", "source_location": "L1236"}, {"caller_nid": "freertos_kernel_stream_buffer_xstreambufferisempty", "callee": "traceRETURN_xStreamBufferIsEmpty", "is_member_call": false, "source_file": "C:\\Users\\akrap\\weather-station\\lib\\tinyusb\\lib\\FreeRTOS-Kernel\\stream_buffer.c", "source_location": "L1250"}, {"caller_nid": "freertos_kernel_stream_buffer_xstreambufferisfull", "callee": "traceENTER_xStreamBufferIsFull", "is_member_call": false, "source_file": "C:\\Users\\akrap\\weather-station\\lib\\tinyusb\\lib\\FreeRTOS-Kernel\\stream_buffer.c", "source_location": "L1262"}, {"caller_nid": "freertos_kernel_stream_buffer_xstreambufferisfull", "callee": "configASSERT", "is_member_call": false, "source_file": "C:\\Users\\akrap\\weather-station\\lib\\tinyusb\\lib\\FreeRTOS-Kernel\\stream_buffer.c", "source_location": "L1264"}, {"caller_nid": "freertos_kernel_stream_buffer_xstreambufferisfull", "callee": "traceRETURN_xStreamBufferIsFull", "is_member_call": false, "source_file": "C:\\Users\\akrap\\weather-station\\lib\\tinyusb\\lib\\FreeRTOS-Kernel\\stream_buffer.c", "source_location": "L1289"}, {"caller_nid": "freertos_kernel_stream_buffer_xstreambuffersendcompletedfromisr", "callee": "traceENTER_xStreamBufferSendCompletedFromISR", "is_member_call": false, "source_file": "C:\\Users\\akrap\\weather-station\\lib\\tinyusb\\lib\\FreeRTOS-Kernel\\stream_buffer.c", "source_location": "L1302"}, {"caller_nid": "freertos_kernel_stream_buffer_xstreambuffersendcompletedfromisr", "callee": "configASSERT", "is_member_call": false, "source_file": "C:\\Users\\akrap\\weather-station\\lib\\tinyusb\\lib\\FreeRTOS-Kernel\\stream_buffer.c", "source_location": "L1304"}, {"caller_nid": "freertos_kernel_stream_buffer_xstreambuffersendcompletedfromisr", "callee": "taskENTER_CRITICAL_FROM_ISR", "is_member_call": false, "source_file": "C:\\Users\\akrap\\weather-station\\lib\\tinyusb\\lib\\FreeRTOS-Kernel\\stream_buffer.c", "source_location": "L1306"}, {"caller_nid": "freertos_kernel_stream_buffer_xstreambuffersendcompletedfromisr", "callee": "xTaskNotifyFromISR", "is_member_call": false, "source_file": "C:\\Users\\akrap\\weather-station\\lib\\tinyusb\\lib\\FreeRTOS-Kernel\\stream_buffer.c", "source_location": "L1310"}, {"caller_nid": "freertos_kernel_stream_buffer_xstreambuffersendcompletedfromisr", "callee": "taskEXIT_CRITICAL_FROM_ISR", "is_member_call": false, "source_file": "C:\\Users\\akrap\\weather-station\\lib\\tinyusb\\lib\\FreeRTOS-Kernel\\stream_buffer.c", "source_location": "L1322"}, {"caller_nid": "freertos_kernel_stream_buffer_xstreambuffersendcompletedfromisr", "callee": "traceRETURN_xStreamBufferSendCompletedFromISR", "is_member_call": false, "source_file": "C:\\Users\\akrap\\weather-station\\lib\\tinyusb\\lib\\FreeRTOS-Kernel\\stream_buffer.c", "source_location": "L1324"}, {"caller_nid": "freertos_kernel_stream_buffer_xstreambufferreceivecompletedfromisr", "callee": "traceENTER_xStreamBufferReceiveCompletedFromISR", "is_member_call": false, "source_file": "C:\\Users\\akrap\\weather-station\\lib\\tinyusb\\lib\\FreeRTOS-Kernel\\stream_buffer.c", "source_location": "L1337"}, {"caller_nid": "freertos_kernel_stream_buffer_xstreambufferreceivecompletedfromisr", "callee": "configASSERT", "is_member_call": false, "source_file": "C:\\Users\\akrap\\weather-station\\lib\\tinyusb\\lib\\FreeRTOS-Kernel\\stream_buffer.c", "source_location": "L1339"}, {"caller_nid": "freertos_kernel_stream_buffer_xstreambufferreceivecompletedfromisr", "callee": "taskENTER_CRITICAL_FROM_ISR", "is_member_call": false, "source_file": "C:\\Users\\akrap\\weather-station\\lib\\tinyusb\\lib\\FreeRTOS-Kernel\\stream_buffer.c", "source_location": "L1341"}, {"caller_nid": "freertos_kernel_stream_buffer_xstreambufferreceivecompletedfromisr", "callee": "xTaskNotifyFromISR", "is_member_call": false, "source_file": "C:\\Users\\akrap\\weather-station\\lib\\tinyusb\\lib\\FreeRTOS-Kernel\\stream_buffer.c", "source_location": "L1345"}, {"caller_nid": "freertos_kernel_stream_buffer_xstreambufferreceivecompletedfromisr", "callee": "taskEXIT_CRITICAL_FROM_ISR", "is_member_call": false, "source_file": "C:\\Users\\akrap\\weather-station\\lib\\tinyusb\\lib\\FreeRTOS-Kernel\\stream_buffer.c", "source_location": "L1357"}, {"caller_nid": "freertos_kernel_stream_buffer_xstreambufferreceivecompletedfromisr", "callee": "traceRETURN_xStreamBufferReceiveCompletedFromISR", "is_member_call": false, "source_file": "C:\\Users\\akrap\\weather-station\\lib\\tinyusb\\lib\\FreeRTOS-Kernel\\stream_buffer.c", "source_location": "L1359"}, {"caller_nid": "freertos_kernel_stream_buffer_prvwritebytestobuffer", "callee": "configASSERT", "is_member_call": false, "source_file": "C:\\Users\\akrap\\weather-station\\lib\\tinyusb\\lib\\FreeRTOS-Kernel\\stream_buffer.c", "source_location": "L1372"}, {"caller_nid": "freertos_kernel_stream_buffer_prvwritebytestobuffer", "callee": "configMIN", "is_member_call": false, "source_file": "C:\\Users\\akrap\\weather-station\\lib\\tinyusb\\lib\\FreeRTOS-Kernel\\stream_buffer.c", "source_location": "L1377"}, {"caller_nid": "freertos_kernel_stream_buffer_prvwritebytestobuffer", "callee": "configASSERT", "is_member_call": false, "source_file": "C:\\Users\\akrap\\weather-station\\lib\\tinyusb\\lib\\FreeRTOS-Kernel\\stream_buffer.c", "source_location": "L1380"}, {"caller_nid": "freertos_kernel_stream_buffer_prvwritebytestobuffer", "callee": "memcpy", "is_member_call": false, "source_file": "C:\\Users\\akrap\\weather-station\\lib\\tinyusb\\lib\\FreeRTOS-Kernel\\stream_buffer.c", "source_location": "L1381"}, {"caller_nid": "freertos_kernel_stream_buffer_prvwritebytestobuffer", "callee": "configASSERT", "is_member_call": false, "source_file": "C:\\Users\\akrap\\weather-station\\lib\\tinyusb\\lib\\FreeRTOS-Kernel\\stream_buffer.c", "source_location": "L1388"}, {"caller_nid": "freertos_kernel_stream_buffer_prvwritebytestobuffer", "callee": "memcpy", "is_member_call": false, "source_file": "C:\\Users\\akrap\\weather-station\\lib\\tinyusb\\lib\\FreeRTOS-Kernel\\stream_buffer.c", "source_location": "L1389"}, {"caller_nid": "freertos_kernel_stream_buffer_prvwritebytestobuffer", "callee": "mtCOVERAGE_TEST_MARKER", "is_member_call": false, "source_file": "C:\\Users\\akrap\\weather-station\\lib\\tinyusb\\lib\\FreeRTOS-Kernel\\stream_buffer.c", "source_location": "L1393"}, {"caller_nid": "freertos_kernel_stream_buffer_prvwritebytestobuffer", "callee": "mtCOVERAGE_TEST_MARKER", "is_member_call": false, "source_file": "C:\\Users\\akrap\\weather-station\\lib\\tinyusb\\lib\\FreeRTOS-Kernel\\stream_buffer.c", "source_location": "L1404"}, {"caller_nid": "freertos_kernel_stream_buffer_prvreadbytesfrombuffer", "callee": "configASSERT", "is_member_call": false, "source_file": "C:\\Users\\akrap\\weather-station\\lib\\tinyusb\\lib\\FreeRTOS-Kernel\\stream_buffer.c", "source_location": "L1418"}, {"caller_nid": "freertos_kernel_stream_buffer_prvreadbytesfrombuffer", "callee": "configMIN", "is_member_call": false, "source_file": "C:\\Users\\akrap\\weather-station\\lib\\tinyusb\\lib\\FreeRTOS-Kernel\\stream_buffer.c", "source_location": "L1423"}, {"caller_nid": "freertos_kernel_stream_buffer_prvreadbytesfrombuffer", "callee": "configASSERT", "is_member_call": false, "source_file": "C:\\Users\\akrap\\weather-station\\lib\\tinyusb\\lib\\FreeRTOS-Kernel\\stream_buffer.c", "source_location": "L1427"}, {"caller_nid": "freertos_kernel_stream_buffer_prvreadbytesfrombuffer", "callee": "configASSERT", "is_member_call": false, "source_file": "C:\\Users\\akrap\\weather-station\\lib\\tinyusb\\lib\\FreeRTOS-Kernel\\stream_buffer.c", "source_location": "L1428"}, {"caller_nid": "freertos_kernel_stream_buffer_prvreadbytesfrombuffer", "callee": "memcpy", "is_member_call": false, "source_file": "C:\\Users\\akrap\\weather-station\\lib\\tinyusb\\lib\\FreeRTOS-Kernel\\stream_buffer.c", "source_location": "L1429"}, {"caller_nid": "freertos_kernel_stream_buffer_prvreadbytesfrombuffer", "callee": "memcpy", "is_member_call": false, "source_file": "C:\\Users\\akrap\\weather-station\\lib\\tinyusb\\lib\\FreeRTOS-Kernel\\stream_buffer.c", "source_location": "L1436"}, {"caller_nid": "freertos_kernel_stream_buffer_prvreadbytesfrombuffer", "callee": "mtCOVERAGE_TEST_MARKER", "is_member_call": false, "source_file": "C:\\Users\\akrap\\weather-station\\lib\\tinyusb\\lib\\FreeRTOS-Kernel\\stream_buffer.c", "source_location": "L1440"}, {"caller_nid": "freertos_kernel_stream_buffer_prvbytesinbuffer", "callee": "mtCOVERAGE_TEST_MARKER", "is_member_call": false, "source_file": "C:\\Users\\akrap\\weather-station\\lib\\tinyusb\\lib\\FreeRTOS-Kernel\\stream_buffer.c", "source_location": "L1469"}, {"caller_nid": "freertos_kernel_stream_buffer_prvinitialisenewstreambuffer", "callee": "configASSERT", "is_member_call": false, "source_file": "C:\\Users\\akrap\\weather-station\\lib\\tinyusb\\lib\\FreeRTOS-Kernel\\stream_buffer.c", "source_location": "L1493"}, {"caller_nid": "freertos_kernel_stream_buffer_prvinitialisenewstreambuffer", "callee": "memset", "is_member_call": false, "source_file": "C:\\Users\\akrap\\weather-station\\lib\\tinyusb\\lib\\FreeRTOS-Kernel\\stream_buffer.c", "source_location": "L1493"}, {"caller_nid": "freertos_kernel_stream_buffer_prvinitialisenewstreambuffer", "callee": "memset", "is_member_call": false, "source_file": "C:\\Users\\akrap\\weather-station\\lib\\tinyusb\\lib\\FreeRTOS-Kernel\\stream_buffer.c", "source_location": "L1497"}, {"caller_nid": "freertos_kernel_stream_buffer_uxstreambuffergetstreambuffernumber", "callee": "traceENTER_uxStreamBufferGetStreamBufferNumber", "is_member_call": false, "source_file": "C:\\Users\\akrap\\weather-station\\lib\\tinyusb\\lib\\FreeRTOS-Kernel\\stream_buffer.c", "source_location": "L1526"}, {"caller_nid": "freertos_kernel_stream_buffer_uxstreambuffergetstreambuffernumber", "callee": "traceRETURN_uxStreamBufferGetStreamBufferNumber", "is_member_call": false, "source_file": "C:\\Users\\akrap\\weather-station\\lib\\tinyusb\\lib\\FreeRTOS-Kernel\\stream_buffer.c", "source_location": "L1528"}, {"caller_nid": "freertos_kernel_stream_buffer_vstreambuffersetstreambuffernumber", "callee": "traceENTER_vStreamBufferSetStreamBufferNumber", "is_member_call": false, "source_file": "C:\\Users\\akrap\\weather-station\\lib\\tinyusb\\lib\\FreeRTOS-Kernel\\stream_buffer.c", "source_location": "L1541"}, {"caller_nid": "freertos_kernel_stream_buffer_vstreambuffersetstreambuffernumber", "callee": "traceRETURN_vStreamBufferSetStreamBufferNumber", "is_member_call": false, "source_file": "C:\\Users\\akrap\\weather-station\\lib\\tinyusb\\lib\\FreeRTOS-Kernel\\stream_buffer.c", "source_location": "L1545"}, {"caller_nid": "freertos_kernel_stream_buffer_ucstreambuffergetstreambuffertype", "callee": "traceENTER_ucStreamBufferGetStreamBufferType", "is_member_call": false, "source_file": "C:\\Users\\akrap\\weather-station\\lib\\tinyusb\\lib\\FreeRTOS-Kernel\\stream_buffer.c", "source_location": "L1555"}, {"caller_nid": "freertos_kernel_stream_buffer_ucstreambuffergetstreambuffertype", "callee": "traceRETURN_ucStreamBufferGetStreamBufferType", "is_member_call": false, "source_file": "C:\\Users\\akrap\\weather-station\\lib\\tinyusb\\lib\\FreeRTOS-Kernel\\stream_buffer.c", "source_location": "L1557"}]}