{"nodes": [{"id": "c_users_akrap_weather_station_lib_tinyusb_hw_bsp_mcx_boards_frdm_mcxa156_clock_config_c", "label": "clock_config.c", "file_type": "code", "source_file": "C:\\Users\\akrap\\weather-station\\lib\\tinyusb\\hw\\bsp\\mcx\\boards\\frdm_mcxa156\\clock_config.c", "source_location": "L1"}, {"id": "frdm_mcxa156_clock_config_board_initbootclocks", "label": "BOARD_InitBootClocks()", "file_type": "code", "source_file": "C:\\Users\\akrap\\weather-station\\lib\\tinyusb\\hw\\bsp\\mcx\\boards\\frdm_mcxa156\\clock_config.c", "source_location": "L52"}, {"id": "frdm_mcxa156_clock_config_board_bootclockfro12m", "label": "BOARD_BootClockFRO12M()", "file_type": "code", "source_file": "C:\\Users\\akrap\\weather-station\\lib\\tinyusb\\hw\\bsp\\mcx\\boards\\frdm_mcxa156\\clock_config.c", "source_location": "L89"}, {"id": "frdm_mcxa156_clock_config_board_bootclockfro24m", "label": "BOARD_BootClockFRO24M()", "file_type": "code", "source_file": "C:\\Users\\akrap\\weather-station\\lib\\tinyusb\\hw\\bsp\\mcx\\boards\\frdm_mcxa156\\clock_config.c", "source_location": "L170"}, {"id": "frdm_mcxa156_clock_config_board_bootclockfro48m", "label": "BOARD_BootClockFRO48M()", "file_type": "code", "source_file": "C:\\Users\\akrap\\weather-station\\lib\\tinyusb\\hw\\bsp\\mcx\\boards\\frdm_mcxa156\\clock_config.c", "source_location": "L253"}, {"id": "frdm_mcxa156_clock_config_board_bootclockfro64m", "label": "BOARD_BootClockFRO64M()", "file_type": "code", "source_file": "C:\\Users\\akrap\\weather-station\\lib\\tinyusb\\hw\\bsp\\mcx\\boards\\frdm_mcxa156\\clock_config.c", "source_location": "L341"}, {"id": "frdm_mcxa156_clock_config_board_bootclockfro96m", "label": "BOARD_BootClockFRO96M()", "file_type": "code", "source_file": "C:\\Users\\akrap\\weather-station\\lib\\tinyusb\\hw\\bsp\\mcx\\boards\\frdm_mcxa156\\clock_config.c", "source_location": "L431"}], "edges": [{"source": "c_users_akrap_weather_station_lib_tinyusb_hw_bsp_mcx_boards_frdm_mcxa156_clock_config_c", "target": "fsl_clock", "relation": "imports", "context": "import", "confidence": "EXTRACTED", "source_file": "C:\\Users\\akrap\\weather-station\\lib\\tinyusb\\hw\\bsp\\mcx\\boards\\frdm_mcxa156\\clock_config.c", "source_location": "L35", "weight": 1.0}, {"source": "c_users_akrap_weather_station_lib_tinyusb_hw_bsp_mcx_boards_frdm_mcxa156_clock_config_c", "target": "clock_config", "relation": "imports", "context": "import", "confidence": "EXTRACTED", "source_file": "C:\\Users\\akrap\\weather-station\\lib\\tinyusb\\hw\\bsp\\mcx\\boards\\frdm_mcxa156\\clock_config.c", "source_location": "L36", "weight": 1.0}, {"source": "c_users_akrap_weather_station_lib_tinyusb_hw_bsp_mcx_boards_frdm_mcxa156_clock_config_c", "target": "fsl_spc", "relation": "imports", "context": "import", "confidence": "EXTRACTED", "source_file": "C:\\Users\\akrap\\weather-station\\lib\\tinyusb\\hw\\bsp\\mcx\\boards\\frdm_mcxa156\\clock_config.c", "source_location": "L37", "weight": 1.0}, {"source": "c_users_akrap_weather_station_lib_tinyusb_hw_bsp_mcx_boards_frdm_mcxa156_clock_config_c", "target": "frdm_mcxa156_clock_config_board_initbootclocks", "relation": "contains", "confidence": "EXTRACTED", "source_file": "C:\\Users\\akrap\\weather-station\\lib\\tinyusb\\hw\\bsp\\mcx\\boards\\frdm_mcxa156\\clock_config.c", "source_location": "L52", "weight": 1.0}, {"source": "c_users_akrap_weather_station_lib_tinyusb_hw_bsp_mcx_boards_frdm_mcxa156_clock_config_c", "target": "frdm_mcxa156_clock_config_board_bootclockfro12m", "relation": "contains", "confidence": "EXTRACTED", "source_file": "C:\\Users\\akrap\\weather-station\\lib\\tinyusb\\hw\\bsp\\mcx\\boards\\frdm_mcxa156\\clock_config.c", "source_location": "L89", "weight": 1.0}, {"source": "c_users_akrap_weather_station_lib_tinyusb_hw_bsp_mcx_boards_frdm_mcxa156_clock_config_c", "target": "frdm_mcxa156_clock_config_board_bootclockfro24m", "relation": "contains", "confidence": "EXTRACTED", "source_file": "C:\\Users\\akrap\\weather-station\\lib\\tinyusb\\hw\\bsp\\mcx\\boards\\frdm_mcxa156\\clock_config.c", "source_location": "L170", "weight": 1.0}, {"source": "c_users_akrap_weather_station_lib_tinyusb_hw_bsp_mcx_boards_frdm_mcxa156_clock_config_c", "target": "frdm_mcxa156_clock_config_board_bootclockfro48m", "relation": "contains", "confidence": "EXTRACTED", "source_file": "C:\\Users\\akrap\\weather-station\\lib\\tinyusb\\hw\\bsp\\mcx\\boards\\frdm_mcxa156\\clock_config.c", "source_location": "L253", "weight": 1.0}, {"source": "c_users_akrap_weather_station_lib_tinyusb_hw_bsp_mcx_boards_frdm_mcxa156_clock_config_c", "target": "frdm_mcxa156_clock_config_board_bootclockfro64m", "relation": "contains", "confidence": "EXTRACTED", "source_file": "C:\\Users\\akrap\\weather-station\\lib\\tinyusb\\hw\\bsp\\mcx\\boards\\frdm_mcxa156\\clock_config.c", "source_location": "L341", "weight": 1.0}, {"source": "c_users_akrap_weather_station_lib_tinyusb_hw_bsp_mcx_boards_frdm_mcxa156_clock_config_c", "target": "frdm_mcxa156_clock_config_board_bootclockfro96m", "relation": "contains", "confidence": "EXTRACTED", "source_file": "C:\\Users\\akrap\\weather-station\\lib\\tinyusb\\hw\\bsp\\mcx\\boards\\frdm_mcxa156\\clock_config.c", "source_location": "L431", "weight": 1.0}, {"source": "frdm_mcxa156_clock_config_board_initbootclocks", "target": "frdm_mcxa156_clock_config_board_bootclockfro96m", "relation": "calls", "context": "call", "confidence": "EXTRACTED", "source_file": "C:\\Users\\akrap\\weather-station\\lib\\tinyusb\\hw\\bsp\\mcx\\boards\\frdm_mcxa156\\clock_config.c", "source_location": "L54", "weight": 1.0}], "raw_calls": [{"caller_nid": "frdm_mcxa156_clock_config_board_bootclockfro12m", "callee": "CLOCK_GetCoreSysClkFreq", "is_member_call": false, "source_file": "C:\\Users\\akrap\\weather-station\\lib\\tinyusb\\hw\\bsp\\mcx\\boards\\frdm_mcxa156\\clock_config.c", "source_location": "L96"}, {"caller_nid": "frdm_mcxa156_clock_config_board_bootclockfro12m", "callee": "SPC_SetActiveModeCoreLDORegulatorConfig", "is_member_call": false, "source_file": "C:\\Users\\akrap\\weather-station\\lib\\tinyusb\\hw\\bsp\\mcx\\boards\\frdm_mcxa156\\clock_config.c", "source_location": "L103"}, {"caller_nid": "frdm_mcxa156_clock_config_board_bootclockfro12m", "callee": "FMU_FCTRL_RWSC", "is_member_call": false, "source_file": "C:\\Users\\akrap\\weather-station\\lib\\tinyusb\\hw\\bsp\\mcx\\boards\\frdm_mcxa156\\clock_config.c", "source_location": "L105"}, {"caller_nid": "frdm_mcxa156_clock_config_board_bootclockfro12m", "callee": "SPC_SetSRAMOperateVoltage", "is_member_call": false, "source_file": "C:\\Users\\akrap\\weather-station\\lib\\tinyusb\\hw\\bsp\\mcx\\boards\\frdm_mcxa156\\clock_config.c", "source_location": "L109"}, {"caller_nid": "frdm_mcxa156_clock_config_board_bootclockfro12m", "callee": "CLOCK_SetupFRO12MClocking", "is_member_call": false, "source_file": "C:\\Users\\akrap\\weather-station\\lib\\tinyusb\\hw\\bsp\\mcx\\boards\\frdm_mcxa156\\clock_config.c", "source_location": "L112"}, {"caller_nid": "frdm_mcxa156_clock_config_board_bootclockfro12m", "callee": "CLOCK_AttachClk", "is_member_call": false, "source_file": "C:\\Users\\akrap\\weather-station\\lib\\tinyusb\\hw\\bsp\\mcx\\boards\\frdm_mcxa156\\clock_config.c", "source_location": "L114"}, {"caller_nid": "frdm_mcxa156_clock_config_board_bootclockfro12m", "callee": "FMU_FCTRL_RWSC", "is_member_call": false, "source_file": "C:\\Users\\akrap\\weather-station\\lib\\tinyusb\\hw\\bsp\\mcx\\boards\\frdm_mcxa156\\clock_config.c", "source_location": "L119"}, {"caller_nid": "frdm_mcxa156_clock_config_board_bootclockfro12m", "callee": "SPC_SetSRAMOperateVoltage", "is_member_call": false, "source_file": "C:\\Users\\akrap\\weather-station\\lib\\tinyusb\\hw\\bsp\\mcx\\boards\\frdm_mcxa156\\clock_config.c", "source_location": "L123"}, {"caller_nid": "frdm_mcxa156_clock_config_board_bootclockfro12m", "callee": "SPC_SetActiveModeCoreLDORegulatorConfig", "is_member_call": false, "source_file": "C:\\Users\\akrap\\weather-station\\lib\\tinyusb\\hw\\bsp\\mcx\\boards\\frdm_mcxa156\\clock_config.c", "source_location": "L127"}, {"caller_nid": "frdm_mcxa156_clock_config_board_bootclockfro12m", "callee": "CLOCK_SetClockDiv", "is_member_call": false, "source_file": "C:\\Users\\akrap\\weather-station\\lib\\tinyusb\\hw\\bsp\\mcx\\boards\\frdm_mcxa156\\clock_config.c", "source_location": "L133"}, {"caller_nid": "frdm_mcxa156_clock_config_board_bootclockfro24m", "callee": "CLOCK_GetCoreSysClkFreq", "is_member_call": false, "source_file": "C:\\Users\\akrap\\weather-station\\lib\\tinyusb\\hw\\bsp\\mcx\\boards\\frdm_mcxa156\\clock_config.c", "source_location": "L177"}, {"caller_nid": "frdm_mcxa156_clock_config_board_bootclockfro24m", "callee": "SPC_SetActiveModeCoreLDORegulatorConfig", "is_member_call": false, "source_file": "C:\\Users\\akrap\\weather-station\\lib\\tinyusb\\hw\\bsp\\mcx\\boards\\frdm_mcxa156\\clock_config.c", "source_location": "L184"}, {"caller_nid": "frdm_mcxa156_clock_config_board_bootclockfro24m", "callee": "FMU_FCTRL_RWSC", "is_member_call": false, "source_file": "C:\\Users\\akrap\\weather-station\\lib\\tinyusb\\hw\\bsp\\mcx\\boards\\frdm_mcxa156\\clock_config.c", "source_location": "L186"}, {"caller_nid": "frdm_mcxa156_clock_config_board_bootclockfro24m", "callee": "SPC_SetSRAMOperateVoltage", "is_member_call": false, "source_file": "C:\\Users\\akrap\\weather-station\\lib\\tinyusb\\hw\\bsp\\mcx\\boards\\frdm_mcxa156\\clock_config.c", "source_location": "L190"}, {"caller_nid": "frdm_mcxa156_clock_config_board_bootclockfro24m", "callee": "CLOCK_SetupFROHFClocking", "is_member_call": false, "source_file": "C:\\Users\\akrap\\weather-station\\lib\\tinyusb\\hw\\bsp\\mcx\\boards\\frdm_mcxa156\\clock_config.c", "source_location": "L193"}, {"caller_nid": "frdm_mcxa156_clock_config_board_bootclockfro24m", "callee": "CLOCK_SetupFRO12MClocking", "is_member_call": false, "source_file": "C:\\Users\\akrap\\weather-station\\lib\\tinyusb\\hw\\bsp\\mcx\\boards\\frdm_mcxa156\\clock_config.c", "source_location": "L195"}, {"caller_nid": "frdm_mcxa156_clock_config_board_bootclockfro24m", "callee": "CLOCK_AttachClk", "is_member_call": false, "source_file": "C:\\Users\\akrap\\weather-station\\lib\\tinyusb\\hw\\bsp\\mcx\\boards\\frdm_mcxa156\\clock_config.c", "source_location": "L197"}, {"caller_nid": "frdm_mcxa156_clock_config_board_bootclockfro24m", "callee": "FMU_FCTRL_RWSC", "is_member_call": false, "source_file": "C:\\Users\\akrap\\weather-station\\lib\\tinyusb\\hw\\bsp\\mcx\\boards\\frdm_mcxa156\\clock_config.c", "source_location": "L202"}, {"caller_nid": "frdm_mcxa156_clock_config_board_bootclockfro24m", "callee": "SPC_SetSRAMOperateVoltage", "is_member_call": false, "source_file": "C:\\Users\\akrap\\weather-station\\lib\\tinyusb\\hw\\bsp\\mcx\\boards\\frdm_mcxa156\\clock_config.c", "source_location": "L206"}, {"caller_nid": "frdm_mcxa156_clock_config_board_bootclockfro24m", "callee": "SPC_SetActiveModeCoreLDORegulatorConfig", "is_member_call": false, "source_file": "C:\\Users\\akrap\\weather-station\\lib\\tinyusb\\hw\\bsp\\mcx\\boards\\frdm_mcxa156\\clock_config.c", "source_location": "L210"}, {"caller_nid": "frdm_mcxa156_clock_config_board_bootclockfro24m", "callee": "CLOCK_SetClockDiv", "is_member_call": false, "source_file": "C:\\Users\\akrap\\weather-station\\lib\\tinyusb\\hw\\bsp\\mcx\\boards\\frdm_mcxa156\\clock_config.c", "source_location": "L216"}, {"caller_nid": "frdm_mcxa156_clock_config_board_bootclockfro24m", "callee": "CLOCK_SetClockDiv", "is_member_call": false, "source_file": "C:\\Users\\akrap\\weather-station\\lib\\tinyusb\\hw\\bsp\\mcx\\boards\\frdm_mcxa156\\clock_config.c", "source_location": "L217"}, {"caller_nid": "frdm_mcxa156_clock_config_board_bootclockfro48m", "callee": "CLOCK_GetCoreSysClkFreq", "is_member_call": false, "source_file": "C:\\Users\\akrap\\weather-station\\lib\\tinyusb\\hw\\bsp\\mcx\\boards\\frdm_mcxa156\\clock_config.c", "source_location": "L260"}, {"caller_nid": "frdm_mcxa156_clock_config_board_bootclockfro48m", "callee": "SPC_SetActiveModeCoreLDORegulatorConfig", "is_member_call": false, "source_file": "C:\\Users\\akrap\\weather-station\\lib\\tinyusb\\hw\\bsp\\mcx\\boards\\frdm_mcxa156\\clock_config.c", "source_location": "L267"}, {"caller_nid": "frdm_mcxa156_clock_config_board_bootclockfro48m", "callee": "FMU_FCTRL_RWSC", "is_member_call": false, "source_file": "C:\\Users\\akrap\\weather-station\\lib\\tinyusb\\hw\\bsp\\mcx\\boards\\frdm_mcxa156\\clock_config.c", "source_location": "L269"}, {"caller_nid": "frdm_mcxa156_clock_config_board_bootclockfro48m", "callee": "SPC_SetSRAMOperateVoltage", "is_member_call": false, "source_file": "C:\\Users\\akrap\\weather-station\\lib\\tinyusb\\hw\\bsp\\mcx\\boards\\frdm_mcxa156\\clock_config.c", "source_location": "L273"}, {"caller_nid": "frdm_mcxa156_clock_config_board_bootclockfro48m", "callee": "CLOCK_SetupFROHFClocking", "is_member_call": false, "source_file": "C:\\Users\\akrap\\weather-station\\lib\\tinyusb\\hw\\bsp\\mcx\\boards\\frdm_mcxa156\\clock_config.c", "source_location": "L276"}, {"caller_nid": "frdm_mcxa156_clock_config_board_bootclockfro48m", "callee": "CLOCK_SetupFRO12MClocking", "is_member_call": false, "source_file": "C:\\Users\\akrap\\weather-station\\lib\\tinyusb\\hw\\bsp\\mcx\\boards\\frdm_mcxa156\\clock_config.c", "source_location": "L278"}, {"caller_nid": "frdm_mcxa156_clock_config_board_bootclockfro48m", "callee": "CLOCK_AttachClk", "is_member_call": false, "source_file": "C:\\Users\\akrap\\weather-station\\lib\\tinyusb\\hw\\bsp\\mcx\\boards\\frdm_mcxa156\\clock_config.c", "source_location": "L280"}, {"caller_nid": "frdm_mcxa156_clock_config_board_bootclockfro48m", "callee": "FMU_FCTRL_RWSC", "is_member_call": false, "source_file": "C:\\Users\\akrap\\weather-station\\lib\\tinyusb\\hw\\bsp\\mcx\\boards\\frdm_mcxa156\\clock_config.c", "source_location": "L285"}, {"caller_nid": "frdm_mcxa156_clock_config_board_bootclockfro48m", "callee": "SPC_SetSRAMOperateVoltage", "is_member_call": false, "source_file": "C:\\Users\\akrap\\weather-station\\lib\\tinyusb\\hw\\bsp\\mcx\\boards\\frdm_mcxa156\\clock_config.c", "source_location": "L289"}, {"caller_nid": "frdm_mcxa156_clock_config_board_bootclockfro48m", "callee": "SPC_SetActiveModeCoreLDORegulatorConfig", "is_member_call": false, "source_file": "C:\\Users\\akrap\\weather-station\\lib\\tinyusb\\hw\\bsp\\mcx\\boards\\frdm_mcxa156\\clock_config.c", "source_location": "L293"}, {"caller_nid": "frdm_mcxa156_clock_config_board_bootclockfro48m", "callee": "CLOCK_SetClockDiv", "is_member_call": false, "source_file": "C:\\Users\\akrap\\weather-station\\lib\\tinyusb\\hw\\bsp\\mcx\\boards\\frdm_mcxa156\\clock_config.c", "source_location": "L299"}, {"caller_nid": "frdm_mcxa156_clock_config_board_bootclockfro48m", "callee": "CLOCK_SetClockDiv", "is_member_call": false, "source_file": "C:\\Users\\akrap\\weather-station\\lib\\tinyusb\\hw\\bsp\\mcx\\boards\\frdm_mcxa156\\clock_config.c", "source_location": "L300"}, {"caller_nid": "frdm_mcxa156_clock_config_board_bootclockfro64m", "callee": "CLOCK_GetCoreSysClkFreq", "is_member_call": false, "source_file": "C:\\Users\\akrap\\weather-station\\lib\\tinyusb\\hw\\bsp\\mcx\\boards\\frdm_mcxa156\\clock_config.c", "source_location": "L348"}, {"caller_nid": "frdm_mcxa156_clock_config_board_bootclockfro64m", "callee": "SPC_SetActiveModeCoreLDORegulatorConfig", "is_member_call": false, "source_file": "C:\\Users\\akrap\\weather-station\\lib\\tinyusb\\hw\\bsp\\mcx\\boards\\frdm_mcxa156\\clock_config.c", "source_location": "L355"}, {"caller_nid": "frdm_mcxa156_clock_config_board_bootclockfro64m", "callee": "FMU_FCTRL_RWSC", "is_member_call": false, "source_file": "C:\\Users\\akrap\\weather-station\\lib\\tinyusb\\hw\\bsp\\mcx\\boards\\frdm_mcxa156\\clock_config.c", "source_location": "L357"}, {"caller_nid": "frdm_mcxa156_clock_config_board_bootclockfro64m", "callee": "SPC_SetSRAMOperateVoltage", "is_member_call": false, "source_file": "C:\\Users\\akrap\\weather-station\\lib\\tinyusb\\hw\\bsp\\mcx\\boards\\frdm_mcxa156\\clock_config.c", "source_location": "L361"}, {"caller_nid": "frdm_mcxa156_clock_config_board_bootclockfro64m", "callee": "CLOCK_SetupFROHFClocking", "is_member_call": false, "source_file": "C:\\Users\\akrap\\weather-station\\lib\\tinyusb\\hw\\bsp\\mcx\\boards\\frdm_mcxa156\\clock_config.c", "source_location": "L364"}, {"caller_nid": "frdm_mcxa156_clock_config_board_bootclockfro64m", "callee": "CLOCK_SetupFRO12MClocking", "is_member_call": false, "source_file": "C:\\Users\\akrap\\weather-station\\lib\\tinyusb\\hw\\bsp\\mcx\\boards\\frdm_mcxa156\\clock_config.c", "source_location": "L366"}, {"caller_nid": "frdm_mcxa156_clock_config_board_bootclockfro64m", "callee": "CLOCK_AttachClk", "is_member_call": false, "source_file": "C:\\Users\\akrap\\weather-station\\lib\\tinyusb\\hw\\bsp\\mcx\\boards\\frdm_mcxa156\\clock_config.c", "source_location": "L368"}, {"caller_nid": "frdm_mcxa156_clock_config_board_bootclockfro64m", "callee": "FMU_FCTRL_RWSC", "is_member_call": false, "source_file": "C:\\Users\\akrap\\weather-station\\lib\\tinyusb\\hw\\bsp\\mcx\\boards\\frdm_mcxa156\\clock_config.c", "source_location": "L373"}, {"caller_nid": "frdm_mcxa156_clock_config_board_bootclockfro64m", "callee": "SPC_SetSRAMOperateVoltage", "is_member_call": false, "source_file": "C:\\Users\\akrap\\weather-station\\lib\\tinyusb\\hw\\bsp\\mcx\\boards\\frdm_mcxa156\\clock_config.c", "source_location": "L377"}, {"caller_nid": "frdm_mcxa156_clock_config_board_bootclockfro64m", "callee": "SPC_SetActiveModeCoreLDORegulatorConfig", "is_member_call": false, "source_file": "C:\\Users\\akrap\\weather-station\\lib\\tinyusb\\hw\\bsp\\mcx\\boards\\frdm_mcxa156\\clock_config.c", "source_location": "L381"}, {"caller_nid": "frdm_mcxa156_clock_config_board_bootclockfro64m", "callee": "CLOCK_SetClockDiv", "is_member_call": false, "source_file": "C:\\Users\\akrap\\weather-station\\lib\\tinyusb\\hw\\bsp\\mcx\\boards\\frdm_mcxa156\\clock_config.c", "source_location": "L387"}, {"caller_nid": "frdm_mcxa156_clock_config_board_bootclockfro64m", "callee": "CLOCK_SetClockDiv", "is_member_call": false, "source_file": "C:\\Users\\akrap\\weather-station\\lib\\tinyusb\\hw\\bsp\\mcx\\boards\\frdm_mcxa156\\clock_config.c", "source_location": "L388"}, {"caller_nid": "frdm_mcxa156_clock_config_board_bootclockfro96m", "callee": "CLOCK_GetCoreSysClkFreq", "is_member_call": false, "source_file": "C:\\Users\\akrap\\weather-station\\lib\\tinyusb\\hw\\bsp\\mcx\\boards\\frdm_mcxa156\\clock_config.c", "source_location": "L438"}, {"caller_nid": "frdm_mcxa156_clock_config_board_bootclockfro96m", "callee": "SPC_SetActiveModeCoreLDORegulatorConfig", "is_member_call": false, "source_file": "C:\\Users\\akrap\\weather-station\\lib\\tinyusb\\hw\\bsp\\mcx\\boards\\frdm_mcxa156\\clock_config.c", "source_location": "L445"}, {"caller_nid": "frdm_mcxa156_clock_config_board_bootclockfro96m", "callee": "FMU_FCTRL_RWSC", "is_member_call": false, "source_file": "C:\\Users\\akrap\\weather-station\\lib\\tinyusb\\hw\\bsp\\mcx\\boards\\frdm_mcxa156\\clock_config.c", "source_location": "L447"}, {"caller_nid": "frdm_mcxa156_clock_config_board_bootclockfro96m", "callee": "SPC_SetSRAMOperateVoltage", "is_member_call": false, "source_file": "C:\\Users\\akrap\\weather-station\\lib\\tinyusb\\hw\\bsp\\mcx\\boards\\frdm_mcxa156\\clock_config.c", "source_location": "L451"}, {"caller_nid": "frdm_mcxa156_clock_config_board_bootclockfro96m", "callee": "CLOCK_SetupFROHFClocking", "is_member_call": false, "source_file": "C:\\Users\\akrap\\weather-station\\lib\\tinyusb\\hw\\bsp\\mcx\\boards\\frdm_mcxa156\\clock_config.c", "source_location": "L454"}, {"caller_nid": "frdm_mcxa156_clock_config_board_bootclockfro96m", "callee": "CLOCK_SetupFRO12MClocking", "is_member_call": false, "source_file": "C:\\Users\\akrap\\weather-station\\lib\\tinyusb\\hw\\bsp\\mcx\\boards\\frdm_mcxa156\\clock_config.c", "source_location": "L456"}, {"caller_nid": "frdm_mcxa156_clock_config_board_bootclockfro96m", "callee": "CLOCK_AttachClk", "is_member_call": false, "source_file": "C:\\Users\\akrap\\weather-station\\lib\\tinyusb\\hw\\bsp\\mcx\\boards\\frdm_mcxa156\\clock_config.c", "source_location": "L458"}, {"caller_nid": "frdm_mcxa156_clock_config_board_bootclockfro96m", "callee": "FMU_FCTRL_RWSC", "is_member_call": false, "source_file": "C:\\Users\\akrap\\weather-station\\lib\\tinyusb\\hw\\bsp\\mcx\\boards\\frdm_mcxa156\\clock_config.c", "source_location": "L463"}, {"caller_nid": "frdm_mcxa156_clock_config_board_bootclockfro96m", "callee": "SPC_SetSRAMOperateVoltage", "is_member_call": false, "source_file": "C:\\Users\\akrap\\weather-station\\lib\\tinyusb\\hw\\bsp\\mcx\\boards\\frdm_mcxa156\\clock_config.c", "source_location": "L467"}, {"caller_nid": "frdm_mcxa156_clock_config_board_bootclockfro96m", "callee": "SPC_SetActiveModeCoreLDORegulatorConfig", "is_member_call": false, "source_file": "C:\\Users\\akrap\\weather-station\\lib\\tinyusb\\hw\\bsp\\mcx\\boards\\frdm_mcxa156\\clock_config.c", "source_location": "L471"}, {"caller_nid": "frdm_mcxa156_clock_config_board_bootclockfro96m", "callee": "CLOCK_SetClockDiv", "is_member_call": false, "source_file": "C:\\Users\\akrap\\weather-station\\lib\\tinyusb\\hw\\bsp\\mcx\\boards\\frdm_mcxa156\\clock_config.c", "source_location": "L477"}, {"caller_nid": "frdm_mcxa156_clock_config_board_bootclockfro96m", "callee": "CLOCK_SetClockDiv", "is_member_call": false, "source_file": "C:\\Users\\akrap\\weather-station\\lib\\tinyusb\\hw\\bsp\\mcx\\boards\\frdm_mcxa156\\clock_config.c", "source_location": "L478"}]}