{"nodes": [{"id": "c_users_akrap_weather_station_lib_tinyusb_hw_bsp_msp430_family_c", "label": "family.c", "file_type": "code", "source_file": "C:\\Users\\akrap\\weather-station\\lib\\tinyusb\\hw\\bsp\\msp430\\family.c", "source_location": "L1"}, {"id": "msp430_family_usb_ubm_isr", "label": "USB_UBM_ISR()", "file_type": "code", "source_file": "C:\\Users\\akrap\\weather-station\\lib\\tinyusb\\hw\\bsp\\msp430\\family.c", "source_location": "L39"}, {"id": "msp430_family_systemclock_config", "label": "SystemClock_Config()", "file_type": "code", "source_file": "C:\\Users\\akrap\\weather-station\\lib\\tinyusb\\hw\\bsp\\msp430\\family.c", "source_location": "L49"}, {"id": "msp430_family_board_init", "label": "board_init()", "file_type": "code", "source_file": "C:\\Users\\akrap\\weather-station\\lib\\tinyusb\\hw\\bsp\\msp430\\family.c", "source_location": "L128"}, {"id": "msp430_family_board_led_write", "label": "board_led_write()", "file_type": "code", "source_file": "C:\\Users\\akrap\\weather-station\\lib\\tinyusb\\hw\\bsp\\msp430\\family.c", "source_location": "L158"}, {"id": "msp430_family_board_button_read", "label": "board_button_read()", "file_type": "code", "source_file": "C:\\Users\\akrap\\weather-station\\lib\\tinyusb\\hw\\bsp\\msp430\\family.c", "source_location": "L170"}, {"id": "msp430_family_board_uart_read", "label": "board_uart_read()", "file_type": "code", "source_file": "C:\\Users\\akrap\\weather-station\\lib\\tinyusb\\hw\\bsp\\msp430\\family.c", "source_location": "L175"}, {"id": "msp430_family_board_uart_write", "label": "board_uart_write()", "file_type": "code", "source_file": "C:\\Users\\akrap\\weather-station\\lib\\tinyusb\\hw\\bsp\\msp430\\family.c", "source_location": "L187"}, {"id": "msp430_family_timer0_a0_isr", "label": "TIMER0_A0_ISR()", "file_type": "code", "source_file": "C:\\Users\\akrap\\weather-station\\lib\\tinyusb\\hw\\bsp\\msp430\\family.c", "source_location": "L207"}, {"id": "msp430_family_tusb_time_millis_api", "label": "tusb_time_millis_api()", "file_type": "code", "source_file": "C:\\Users\\akrap\\weather-station\\lib\\tinyusb\\hw\\bsp\\msp430\\family.c", "source_location": "L212"}], "edges": [{"source": "c_users_akrap_weather_station_lib_tinyusb_hw_bsp_msp430_family_c", "target": "board_api", "relation": "imports", "context": "import", "confidence": "EXTRACTED", "source_file": "C:\\Users\\akrap\\weather-station\\lib\\tinyusb\\hw\\bsp\\msp430\\family.c", "source_location": "L31", "weight": 1.0}, {"source": "c_users_akrap_weather_station_lib_tinyusb_hw_bsp_msp430_family_c", "target": "board", "relation": "imports", "context": "import", "confidence": "EXTRACTED", "source_file": "C:\\Users\\akrap\\weather-station\\lib\\tinyusb\\hw\\bsp\\msp430\\family.c", "source_location": "L32", "weight": 1.0}, {"source": "c_users_akrap_weather_station_lib_tinyusb_hw_bsp_msp430_family_c", "target": "msp430", "relation": "imports", "context": "import", "confidence": "EXTRACTED", "source_file": "C:\\Users\\akrap\\weather-station\\lib\\tinyusb\\hw\\bsp\\msp430\\family.c", "source_location": "L33", "weight": 1.0}, {"source": "c_users_akrap_weather_station_lib_tinyusb_hw_bsp_msp430_family_c", "target": "msp430_family_usb_ubm_isr", "relation": "contains", "confidence": "EXTRACTED", "source_file": "C:\\Users\\akrap\\weather-station\\lib\\tinyusb\\hw\\bsp\\msp430\\family.c", "source_location": "L39", "weight": 1.0}, {"source": "c_users_akrap_weather_station_lib_tinyusb_hw_bsp_msp430_family_c", "target": "msp430_family_systemclock_config", "relation": "contains", "confidence": "EXTRACTED", "source_file": "C:\\Users\\akrap\\weather-station\\lib\\tinyusb\\hw\\bsp\\msp430\\family.c", "source_location": "L49", "weight": 1.0}, {"source": "c_users_akrap_weather_station_lib_tinyusb_hw_bsp_msp430_family_c", "target": "msp430_family_board_init", "relation": "contains", "confidence": "EXTRACTED", "source_file": "C:\\Users\\akrap\\weather-station\\lib\\tinyusb\\hw\\bsp\\msp430\\family.c", "source_location": "L128", "weight": 1.0}, {"source": "c_users_akrap_weather_station_lib_tinyusb_hw_bsp_msp430_family_c", "target": "msp430_family_board_led_write", "relation": "contains", "confidence": "EXTRACTED", "source_file": "C:\\Users\\akrap\\weather-station\\lib\\tinyusb\\hw\\bsp\\msp430\\family.c", "source_location": "L158", "weight": 1.0}, {"source": "c_users_akrap_weather_station_lib_tinyusb_hw_bsp_msp430_family_c", "target": "msp430_family_board_button_read", "relation": "contains", "confidence": "EXTRACTED", "source_file": "C:\\Users\\akrap\\weather-station\\lib\\tinyusb\\hw\\bsp\\msp430\\family.c", "source_location": "L170", "weight": 1.0}, {"source": "c_users_akrap_weather_station_lib_tinyusb_hw_bsp_msp430_family_c", "target": "msp430_family_board_uart_read", "relation": "contains", "confidence": "EXTRACTED", "source_file": "C:\\Users\\akrap\\weather-station\\lib\\tinyusb\\hw\\bsp\\msp430\\family.c", "source_location": "L175", "weight": 1.0}, {"source": "c_users_akrap_weather_station_lib_tinyusb_hw_bsp_msp430_family_c", "target": "msp430_family_board_uart_write", "relation": "contains", "confidence": "EXTRACTED", "source_file": "C:\\Users\\akrap\\weather-station\\lib\\tinyusb\\hw\\bsp\\msp430\\family.c", "source_location": "L187", "weight": 1.0}, {"source": "c_users_akrap_weather_station_lib_tinyusb_hw_bsp_msp430_family_c", "target": "msp430_family_timer0_a0_isr", "relation": "contains", "confidence": "EXTRACTED", "source_file": "C:\\Users\\akrap\\weather-station\\lib\\tinyusb\\hw\\bsp\\msp430\\family.c", "source_location": "L207", "weight": 1.0}, {"source": "c_users_akrap_weather_station_lib_tinyusb_hw_bsp_msp430_family_c", "target": "msp430_family_tusb_time_millis_api", "relation": "contains", "confidence": "EXTRACTED", "source_file": "C:\\Users\\akrap\\weather-station\\lib\\tinyusb\\hw\\bsp\\msp430\\family.c", "source_location": "L212", "weight": 1.0}, {"source": "msp430_family_systemclock_config", "target": "msp430_family_tusb_time_millis_api", "relation": "calls", "context": "call", "confidence": "EXTRACTED", "source_file": "C:\\Users\\akrap\\weather-station\\lib\\tinyusb\\hw\\bsp\\msp430\\family.c", "source_location": "L105", "weight": 1.0}, {"source": "msp430_family_board_init", "target": "msp430_family_systemclock_config", "relation": "calls", "context": "call", "confidence": "EXTRACTED", "source_file": "C:\\Users\\akrap\\weather-station\\lib\\tinyusb\\hw\\bsp\\msp430\\family.c", "source_location": "L131", "weight": 1.0}], "raw_calls": [{"caller_nid": "msp430_family_usb_ubm_isr", "callee": "tud_int_handler", "is_member_call": false, "source_file": "C:\\Users\\akrap\\weather-station\\lib\\tinyusb\\hw\\bsp\\msp430\\family.c", "source_location": "L40"}, {"caller_nid": "msp430_family_board_init", "callee": "__bis_SR_register", "is_member_call": false, "source_file": "C:\\Users\\akrap\\weather-station\\lib\\tinyusb\\hw\\bsp\\msp430\\family.c", "source_location": "L130"}]}