{"nodes": [{"id": "c_users_akrap_weather_station_lib_tinyusb_lib_cmsis_5_cmsis_dsp_testing_frameworkinclude_timing_h", "label": "Timing.h", "file_type": "code", "source_file": "C:\\Users\\akrap\\weather-station\\lib\\tinyusb\\lib\\CMSIS_5\\CMSIS\\DSP\\Testing\\FrameworkInclude\\Timing.h", "source_location": "L1"}, {"id": "frameworkinclude_timing_startsection", "label": "startSection()", "file_type": "code", "source_file": "C:\\Users\\akrap\\weather-station\\lib\\tinyusb\\lib\\CMSIS_5\\CMSIS\\DSP\\Testing\\FrameworkInclude\\Timing.h", "source_location": "L27"}, {"id": "frameworkinclude_timing_stopsection", "label": "stopSection()", "file_type": "code", "source_file": "C:\\Users\\akrap\\weather-station\\lib\\tinyusb\\lib\\CMSIS_5\\CMSIS\\DSP\\Testing\\FrameworkInclude\\Timing.h", "source_location": "L59"}], "edges": [{"source": "c_users_akrap_weather_station_lib_tinyusb_lib_cmsis_5_cmsis_dsp_testing_frameworkinclude_timing_h", "target": "test", "relation": "imports", "context": "import", "confidence": "EXTRACTED", "source_file": "C:\\Users\\akrap\\weather-station\\lib\\tinyusb\\lib\\CMSIS_5\\CMSIS\\DSP\\Testing\\FrameworkInclude\\Timing.h", "source_location": "L4", "weight": 1.0}, {"source": "c_users_akrap_weather_station_lib_tinyusb_lib_cmsis_5_cmsis_dsp_testing_frameworkinclude_timing_h", "target": "arm_math_types", "relation": "imports", "context": "import", "confidence": "EXTRACTED", "source_file": "C:\\Users\\akrap\\weather-station\\lib\\tinyusb\\lib\\CMSIS_5\\CMSIS\\DSP\\Testing\\FrameworkInclude\\Timing.h", "source_location": "L5", "weight": 1.0}, {"source": "c_users_akrap_weather_station_lib_tinyusb_lib_cmsis_5_cmsis_dsp_testing_frameworkinclude_timing_h", "target": "arm_math_types_f16", "relation": "imports", "context": "import", "confidence": "EXTRACTED", "source_file": "C:\\Users\\akrap\\weather-station\\lib\\tinyusb\\lib\\CMSIS_5\\CMSIS\\DSP\\Testing\\FrameworkInclude\\Timing.h", "source_location": "L6", "weight": 1.0}, {"source": "c_users_akrap_weather_station_lib_tinyusb_lib_cmsis_5_cmsis_dsp_testing_frameworkinclude_timing_h", "target": "frameworkinclude_timing_startsection", "relation": "contains", "confidence": "EXTRACTED", "source_file": "C:\\Users\\akrap\\weather-station\\lib\\tinyusb\\lib\\CMSIS_5\\CMSIS\\DSP\\Testing\\FrameworkInclude\\Timing.h", "source_location": "L27", "weight": 1.0}, {"source": "c_users_akrap_weather_station_lib_tinyusb_lib_cmsis_5_cmsis_dsp_testing_frameworkinclude_timing_h", "target": "frameworkinclude_timing_stopsection", "relation": "contains", "confidence": "EXTRACTED", "source_file": "C:\\Users\\akrap\\weather-station\\lib\\tinyusb\\lib\\CMSIS_5\\CMSIS\\DSP\\Testing\\FrameworkInclude\\Timing.h", "source_location": "L59", "weight": 1.0}], "raw_calls": [{"caller_nid": "frameworkinclude_timing_startsection", "callee": "startSectionNB", "is_member_call": false, "source_file": "C:\\Users\\akrap\\weather-station\\lib\\tinyusb\\lib\\CMSIS_5\\CMSIS\\DSP\\Testing\\FrameworkInclude\\Timing.h", "source_location": "L31"}, {"caller_nid": "frameworkinclude_timing_startsection", "callee": "startSectionNB", "is_member_call": false, "source_file": "C:\\Users\\akrap\\weather-station\\lib\\tinyusb\\lib\\CMSIS_5\\CMSIS\\DSP\\Testing\\FrameworkInclude\\Timing.h", "source_location": "L34"}, {"caller_nid": "frameworkinclude_timing_startsection", "callee": "startSectionNB", "is_member_call": false, "source_file": "C:\\Users\\akrap\\weather-station\\lib\\tinyusb\\lib\\CMSIS_5\\CMSIS\\DSP\\Testing\\FrameworkInclude\\Timing.h", "source_location": "L37"}, {"caller_nid": "frameworkinclude_timing_startsection", "callee": "startSectionNB", "is_member_call": false, "source_file": "C:\\Users\\akrap\\weather-station\\lib\\tinyusb\\lib\\CMSIS_5\\CMSIS\\DSP\\Testing\\FrameworkInclude\\Timing.h", "source_location": "L40"}, {"caller_nid": "frameworkinclude_timing_startsection", "callee": "startSectionNB", "is_member_call": false, "source_file": "C:\\Users\\akrap\\weather-station\\lib\\tinyusb\\lib\\CMSIS_5\\CMSIS\\DSP\\Testing\\FrameworkInclude\\Timing.h", "source_location": "L43"}, {"caller_nid": "frameworkinclude_timing_startsection", "callee": "startSectionNB", "is_member_call": false, "source_file": "C:\\Users\\akrap\\weather-station\\lib\\tinyusb\\lib\\CMSIS_5\\CMSIS\\DSP\\Testing\\FrameworkInclude\\Timing.h", "source_location": "L46"}, {"caller_nid": "frameworkinclude_timing_startsection", "callee": "startSectionNB", "is_member_call": false, "source_file": "C:\\Users\\akrap\\weather-station\\lib\\tinyusb\\lib\\CMSIS_5\\CMSIS\\DSP\\Testing\\FrameworkInclude\\Timing.h", "source_location": "L49"}, {"caller_nid": "frameworkinclude_timing_startsection", "callee": "startSectionNB", "is_member_call": false, "source_file": "C:\\Users\\akrap\\weather-station\\lib\\tinyusb\\lib\\CMSIS_5\\CMSIS\\DSP\\Testing\\FrameworkInclude\\Timing.h", "source_location": "L52"}, {"caller_nid": "frameworkinclude_timing_startsection", "callee": "startSectionNB", "is_member_call": false, "source_file": "C:\\Users\\akrap\\weather-station\\lib\\tinyusb\\lib\\CMSIS_5\\CMSIS\\DSP\\Testing\\FrameworkInclude\\Timing.h", "source_location": "L55"}, {"caller_nid": "frameworkinclude_timing_stopsection", "callee": "stopSectionNB", "is_member_call": false, "source_file": "C:\\Users\\akrap\\weather-station\\lib\\tinyusb\\lib\\CMSIS_5\\CMSIS\\DSP\\Testing\\FrameworkInclude\\Timing.h", "source_location": "L63"}, {"caller_nid": "frameworkinclude_timing_stopsection", "callee": "stopSectionNB", "is_member_call": false, "source_file": "C:\\Users\\akrap\\weather-station\\lib\\tinyusb\\lib\\CMSIS_5\\CMSIS\\DSP\\Testing\\FrameworkInclude\\Timing.h", "source_location": "L66"}, {"caller_nid": "frameworkinclude_timing_stopsection", "callee": "stopSectionNB", "is_member_call": false, "source_file": "C:\\Users\\akrap\\weather-station\\lib\\tinyusb\\lib\\CMSIS_5\\CMSIS\\DSP\\Testing\\FrameworkInclude\\Timing.h", "source_location": "L69"}, {"caller_nid": "frameworkinclude_timing_stopsection", "callee": "stopSectionNB", "is_member_call": false, "source_file": "C:\\Users\\akrap\\weather-station\\lib\\tinyusb\\lib\\CMSIS_5\\CMSIS\\DSP\\Testing\\FrameworkInclude\\Timing.h", "source_location": "L72"}, {"caller_nid": "frameworkinclude_timing_stopsection", "callee": "stopSectionNB", "is_member_call": false, "source_file": "C:\\Users\\akrap\\weather-station\\lib\\tinyusb\\lib\\CMSIS_5\\CMSIS\\DSP\\Testing\\FrameworkInclude\\Timing.h", "source_location": "L75"}, {"caller_nid": "frameworkinclude_timing_stopsection", "callee": "stopSectionNB", "is_member_call": false, "source_file": "C:\\Users\\akrap\\weather-station\\lib\\tinyusb\\lib\\CMSIS_5\\CMSIS\\DSP\\Testing\\FrameworkInclude\\Timing.h", "source_location": "L78"}, {"caller_nid": "frameworkinclude_timing_stopsection", "callee": "stopSectionNB", "is_member_call": false, "source_file": "C:\\Users\\akrap\\weather-station\\lib\\tinyusb\\lib\\CMSIS_5\\CMSIS\\DSP\\Testing\\FrameworkInclude\\Timing.h", "source_location": "L81"}, {"caller_nid": "frameworkinclude_timing_stopsection", "callee": "stopSectionNB", "is_member_call": false, "source_file": "C:\\Users\\akrap\\weather-station\\lib\\tinyusb\\lib\\CMSIS_5\\CMSIS\\DSP\\Testing\\FrameworkInclude\\Timing.h", "source_location": "L84"}, {"caller_nid": "frameworkinclude_timing_stopsection", "callee": "stopSectionNB", "is_member_call": false, "source_file": "C:\\Users\\akrap\\weather-station\\lib\\tinyusb\\lib\\CMSIS_5\\CMSIS\\DSP\\Testing\\FrameworkInclude\\Timing.h", "source_location": "L87"}]}